day3/alu.v
module alu(
    input  wire [3:0] a,
    input  wire [3:0] b,
    input  wire [2:0] op,
    output reg  [4:0] result,
    output reg        zero
);

    // Operations
    parameter ADD = 3'b000;
    parameter SUB = 3'b001;
    parameter AND = 3'b010;
    parameter OR  = 3'b011;
    parameter XOR = 3'b100;
    parameter NOT = 3'b101;
    parameter SHL = 3'b110;
    parameter SHR = 3'b111;

    always @(*) begin
        case (op)
            ADD: result = a + b;
            SUB: result = a - b;
            AND: result = a & b;
            OR:  result = a | b;
            XOR: result = a ^ b;
            NOT: result = ~a;
            SHL: result = a << 1;
            SHR: result = a >> 1;
            default: result = 0;
        endcase
        zero = (result == 0) ? 1 : 0;
    end

endmodule

day7/reg_file.v
module reg_file(
    input  wire        clk,
    input  wire        rst,
    input  wire        wr_en,
    input  wire [2:0]  wr_addr,
    input  wire [7:0]  wr_data,
    input  wire [2:0]  rd_addr1,
    input  wire [2:0]  rd_addr2,
    output wire [7:0]  rd_data1,
    output wire [7:0]  rd_data2
);
    // 8 registers, har ek 8-bit
    reg [7:0] registers [0:7];
    integer i;

    // Write operation
    always @(posedge clk or posedge rst) begin
        if (rst) begin
            for (i=0; i<8; i=i+1)
                registers[i] <= 8'b0;
        end
        else if (wr_en) begin
            registers[wr_addr] <= wr_data;
        end
    end

    // Read operation
    assign rd_data1 = registers[rd_addr1];
    assign rd_data2 = registers[rd_addr2];

endmodule

day7/imem.v
module imem(
    input  wire [2:0] addr,
    output reg  [7:0] instruction
);
    // 8 instructions ka program stored hai
    always @(*) begin
        case (addr)
            3'd0: instruction = 8'b00_000_001; // ADD R0+R1
            3'd1: instruction = 8'b00_010_011; // ADD R2+R3
            3'd2: instruction = 8'b01_000_010; // SUB R0-R2
            3'd3: instruction = 8'b10_001_011; // AND R1&R3
            3'd4: instruction = 8'b11_000_001; // OR  R0|R1
            3'd5: instruction = 8'b00_100_101; // ADD R4+R5
            3'd6: instruction = 8'b01_110_111; // SUB R6-R7
            3'd7: instruction = 8'b10_000_001; // AND R0&R1
            default: instruction = 8'b0;
        endcase
    end
endmodule

day6/pc.v
module pc(
    input  wire       clk,
    input  wire       rst,
    input  wire       halt,
    output reg  [2:0] pc_out
);
    always @(posedge clk or posedge rst) begin
        if (rst)
            pc_out <= 3'd0;
        else if (!halt) begin
            if (pc_out == 3'd7)
                pc_out <= 3'd0;  // Wapas start pe
            else
                pc_out <= pc_out + 1;
        end
    end
endmodule

day7/cpu_v2.v
module cpu_v2(
    input  wire clk,
    input  wire rst,
    output wire [7:0] result,
    output wire [2:0] pc_out
);
    wire [7:0] instruction;
    wire [1:0] opcode  = instruction[7:6];
    wire [2:0] reg_a   = instruction[5:3];
    wire [2:0] reg_b   = instruction[2:0];

    wire [7:0] data_a, data_b;
    wire [4:0] alu_out;
    reg  [2:0] alu_op;

    // Program Counter
    pc PC (
        .clk(clk), .rst(rst),
        .halt(1'b0),
        .pc_out(pc_out)
    );

    // Instruction Memory
    imem IMEM (
        .addr(pc_out),
        .instruction(instruction)
    );

    // Register File
    reg_file RF (
        .clk(clk), .rst(rst),
        .wr_en(1'b1),
        .wr_addr(reg_a),
        .wr_data({3'b0, alu_out}),
        .rd_addr1(reg_a),
        .rd_addr2(reg_b),
        .rd_data1(data_a),
        .rd_data2(data_b)
    );

    // ALU
    alu ALU (
        .a(data_a[3:0]),
        .b(data_b[3:0]),
        .op(alu_op),
        .result(alu_out),
        .zero()
    );

    always @(*) begin
        case (opcode)
            2'b00: alu_op = 3'b000; // ADD
            2'b01: alu_op = 3'b001; // SUB
            2'b10: alu_op = 3'b010; // AND
            2'b11: alu_op = 3'b011; // OR
        endcase
    end

    assign result = {3'b0, alu_out};

endmodule

day6/cpu_v2_tb.v
module cpu_v2_tb;

    reg        clk, rst;
    wire [7:0] result;
    wire [2:0] pc_out;

    cpu_v2 uut (
        .clk(clk), .rst(rst),
        .result(result),
        .pc_out(pc_out)
    );

    initial clk = 0;
    always #5 clk = ~clk;

    initial begin
        $dumpfile("cpu_v2.vcd");
        $dumpvars(0, cpu_v2_tb);

        rst=1; #20;
        rst=0;

        // 8 instructions execute karo
        repeat(10) begin
            #10;
            $display("PC=%0d | Instruction running | Result=%0d",
                      pc_out, result);
        end

        $display("Day 6 Complete! CPU with Program Counter working!");
        $finish;
    end

endmodule

day6/cpu_v2.vcd
$date
	Mon Jul 27 18:47:55 2026
$end
$version
	Icarus Verilog
$end
$timescale
	1s
$end
$scope module cpu_v2_tb $end
$var wire 8 ! result [7:0] $end
$var wire 3 " pc_out [2:0] $end
$var reg 1 # clk $end
$var reg 1 $ rst $end
$scope module uut $end
$var wire 1 # clk $end
$var wire 1 $ rst $end
$var wire 8 % result [7:0] $end
$var wire 3 & reg_b [2:0] $end
$var wire 3 ' reg_a [2:0] $end
$var wire 3 ( pc_out [2:0] $end
$var wire 2 ) opcode [1:0] $end
$var wire 8 * instruction [7:0] $end
$var wire 8 + data_b [7:0] $end
$var wire 8 , data_a [7:0] $end
$var wire 5 - alu_out [4:0] $end
$var reg 3 . alu_op [2:0] $end
$scope module ALU $end
$var wire 4 / a [3:0] $end
$var wire 4 0 b [3:0] $end
$var wire 3 1 op [2:0] $end
$var parameter 3 2 ADD $end
$var parameter 3 3 AND $end
$var parameter 3 4 NOT $end
$var parameter 3 5 OR $end
$var parameter 3 6 SHL $end
$var parameter 3 7 SHR $end
$var parameter 3 8 SUB $end
$var parameter 3 9 XOR $end
$var reg 5 : result [4:0] $end
$var reg 1 ; zero $end
$upscope $end
$scope module IMEM $end
$var wire 3 < addr [2:0] $end
$var reg 8 = instruction [7:0] $end
$upscope $end
$scope module PC $end
$var wire 1 # clk $end
$var wire 1 > halt $end
$var wire 1 $ rst $end
$var reg 3 ? pc_out [2:0] $end
$upscope $end
$scope module RF $end
$var wire 1 # clk $end
$var wire 3 @ rd_addr1 [2:0] $end
$var wire 3 A rd_addr2 [2:0] $end
$var wire 8 B rd_data1 [7:0] $end
$var wire 8 C rd_data2 [7:0] $end
$var wire 1 $ rst $end
$var wire 3 D wr_addr [2:0] $end
$var wire 8 E wr_data [7:0] $end
$var wire 1 F wr_en $end
$var integer 32 G i [31:0] $end
$upscope $end
$upscope $end
$upscope $end
$enddefinitions $end
$comment Show the parameter values. $end
$dumpall
b100 9
b1 8
b111 7
b110 6
b11 5
b101 4
b10 3
b0 2
$end
#0
$dumpvars
b1000 G
1F
b0 E
b0 D
b0 C
b0 B
b1 A
b0 @
b0 ?
0>
b1 =
b0 <
1;
b0 :
b0 1
b0 0
b0 /
b0 .
b0 -
b0 ,
b0 +
b1 *
b0 )
b0 (
b0 '
b1 &
b0 %
1$
0#
b0 "
b0 !
$end
#5
b1000 G
1#
#10
0#
#15
b1000 G
1#
#20
0#
0$
#25
b11 &
b11 A
b10 '
b10 @
b10 D
b10011 *
b10011 =
b1 "
b1 (
b1 <
b1 ?
1#
#30
0#
#35
b1 .
b1 1
b10 &
b10 A
b0 '
b0 @
b0 D
b1 )
b1000010 *
b1000010 =
b10 "
b10 (
b10 <
b10 ?
1#
#40
0#
#45
b10 .
b10 1
b11 &
b11 A
b1 '
b1 @
b1 D
b10 )
b10001011 *
b10001011 =
b11 "
b11 (
b11 <
b11 ?
1#
#50
0#
#55
b11 .
b11 1
b1 &
b1 A
b0 '
b0 @
b0 D
b11 )
b11000001 *
b11000001 =
b100 "
b100 (
b100 <
b100 ?
1#
#60
0#
#65
b0 .
b0 1
b101 &
b101 A
b100 '
b100 @
b100 D
b0 )
b100101 *
b100101 =
b101 "
b101 (
b101 <
b101 ?
1#
#70
0#
#75
b1 .
b1 1
b111 &
b111 A
b110 '
b110 @
b110 D
b1 )
b1110111 *
b1110111 =
b110 "
b110 (
b110 <
b110 ?
1#
#80
0#
#85
b10 .
b10 1
b1 &
b1 A
b0 '
b0 @
b0 D
b10 )
b10000001 *
b10000001 =
b111 "
b111 (
b111 <
b111 ?
1#
#90
0#
#95
b0 .
b0 1
b0 )
b1 *
b1 =
b0 "
b0 (
b0 <
b0 ?
1#
#100
0#
#105
b11 &
b11 A
b10 '
b10 @
b10 D
b10011 *
b10011 =
b1 "
b1 (
b1 <
b1 ?
1#
#110
0#
#115
b1 .
b1 1
b10 &
b10 A
b0 '
b0 @
b0 D
b1 )
b1000010 *
b1000010 =
b10 "
b10 (
b10 <
b10 ?
1#
