day20/integrated_v3/puf.v
module puf(
    input  wire        clk,
    input  wire        rst,
    input  wire        enable,
    input  wire [7:0]  challenge,
    output reg  [63:0] response,
    output reg         valid
);
    // SRAM PUF simulation
    // Real chip mein: SRAM power-up state
    // random hoti hai per-chip — physically unique
    // Simulation mein: challenge-based deterministic model

    parameter IDLE    = 2'd0;
    parameter SAMPLE  = 2'd1;
    parameter PROCESS = 2'd2;
    parameter DONE    = 2'd3;

    reg [1:0]  state;
    reg [3:0]  count;
    reg [63:0] raw_bits;
    reg [63:0] chip_id;

    // Simulated per-chip unique ID
    // Real silicon mein yeh manufacturing variation se aata hai
    initial chip_id = 64'hDEADBEEF_CAFEBABE;

    // PUF response generation
    function [63:0] puf_response;
        input [7:0]  challenge;
        input [63:0] uid;
        reg   [63:0] resp;
        integer i;
        begin
            resp = uid;
            for (i=0; i<8; i=i+1) begin
                if (challenge[i])
                    resp = {resp[62:0], resp[63]} ^ uid;
                else
                    resp = {resp[0], resp[63:1]} ^ ~uid;
            end
            puf_response = resp;
        end
    endfunction

    always @(posedge clk or posedge rst) begin
        if (rst) begin
            state    <= IDLE;
            response <= 64'h0;
            valid    <= 0;
            count    <= 0;
            raw_bits <= 0;
        end
        else begin
            case (state)
                IDLE: begin
                    valid <= 0;
                    if (enable) begin
                        count    <= 0;
                        raw_bits <= 0;
                        state    <= SAMPLE;
                    end
                end

                SAMPLE: begin
                    raw_bits <= puf_response(challenge, chip_id);
                    count    <= count + 1;
                    if (count == 4'd7)
                        state <= PROCESS;
                end

                PROCESS: begin
                    // Von Neumann debiasing
                    response <= raw_bits ^ (raw_bits >> 32);
                    state    <= DONE;
                end

                DONE: begin
                    valid <= 1;
                    state <= IDLE;
                end
            endcase
        end
    end
endmodule

day20/puf_key.v
module puf_key(
    input  wire        clk,
    input  wire        rst,
    input  wire        start,
    output reg  [127:0] device_key,
    output reg          key_ready
);
    wire [63:0] puf_resp1, puf_resp2;
    wire        puf_valid1, puf_valid2;
    reg         puf_en1, puf_en2;

    // Two PUF instances — 64+64 = 128-bit key
    puf PUF1 (
        .clk(clk), .rst(rst),
        .enable(puf_en1),
        .challenge(8'hA5),
        .response(puf_resp1),
        .valid(puf_valid1)
    );

    puf PUF2 (
        .clk(clk), .rst(rst),
        .enable(puf_en2),
        .challenge(8'h5A),
        .response(puf_resp2),
        .valid(puf_valid2)
    );

    parameter IDLE    = 3'd0;
    parameter PUF1_EN = 3'd1;
    parameter WAIT1   = 3'd2;
    parameter PUF2_EN = 3'd3;
    parameter WAIT2   = 3'd4;
    parameter COMBINE = 3'd5;

    reg [2:0] state;

    always @(posedge clk or posedge rst) begin
        if (rst) begin
            state      <= IDLE;
            puf_en1    <= 0;
            puf_en2    <= 0;
            device_key <= 0;
            key_ready  <= 0;
        end
        else begin
            case (state)
                IDLE: begin
                    key_ready <= 0;
                    if (start) begin
                        puf_en1 <= 1;
                        state   <= PUF1_EN;
                    end
                end

                PUF1_EN: begin
                    puf_en1 <= 0;
                    state   <= WAIT1;
                end

                WAIT1: begin
                    if (puf_valid1) begin
                        puf_en2 <= 1;
                        state   <= PUF2_EN;
                    end
                end

                PUF2_EN: begin
                    puf_en2 <= 0;
                    state   <= WAIT2;
                end

                WAIT2: begin
                    if (puf_valid2)
                        state <= COMBINE;
                end

                COMBINE: begin
                    // 128-bit key = PUF1 || PUF2
                    device_key <= {puf_resp1, puf_resp2};
                    key_ready  <= 1;
                    state      <= IDLE;
                end
            endcase
        end
    end
endmodule

day19/puf_tb.v
module puf_tb;

    reg         clk, rst, start;
    wire [127:0] device_key;
    wire         key_ready;

    puf_key DUT (
        .clk(clk), .rst(rst),
        .start(start),
        .device_key(device_key),
        .key_ready(key_ready)
    );

    initial clk = 0;
    always #5 clk = ~clk;

    reg [127:0] key1, key2;

    initial begin
        $dumpfile("puf.vcd");
        $dumpvars(0, puf_tb);

        rst=1; start=0; #30;
        rst=0; #20;

        $display("================================");
        $display("   BharatSE PUF KEY TEST       ");
        $display("================================");

        // Test 1: Pehli baar key generate karo
        $display("--- Test 1: First Key Gen ---");
        start=1; #10; start=0;
        wait(key_ready);
        key1 = device_key;
        $display("Device Key 1: %h", device_key);
        $display("PASS: Key generated!");
        #50;

        // Test 2: Dobara generate karo — same hona chahiye
        $display("--- Test 2: Reproducibility ---");
        start=1; #10; start=0;
        wait(key_ready);
        key2 = device_key;
        $display("Device Key 2: %h", device_key);

        if(key1 == key2)
            $display("PASS: Same key reproduced!");
        else
            $display("FAIL: Keys differ");
        #50;

        // Test 3: Key zero nahi hona chahiye
        $display("--- Test 3: Non-Zero Check ---");
        if(device_key != 128'h0)
            $display("PASS: Key is non-zero!");
        else
            $display("FAIL: Key is zero");

        // Test 4: Key all-ones nahi hona chahiye
        if(device_key != 128'hFFFFFFFFFFFFFFFFFFFFFFFFFFFFFFFF)
            $display("PASS: Key not all-ones!");
        else
            $display("FAIL: Key is all-ones");

        $display("================================");
        $display("Day 19 Complete!");
        $display("PUF Block working!");
        $display("128-bit Unclonable Key Ready!");
        $display("BharatSE Block 4 DONE!");
        $display("================================");
        $finish;
    end
endmodule

day19/puf.vcd
$date
	Wed Jul 29 02:34:18 2026
$end
$version
	Icarus Verilog
$end
$timescale
	1s
$end
$scope module puf_tb $end
$var wire 1 ! key_ready $end
$var wire 128 " device_key [127:0] $end
$var reg 1 # clk $end
$var reg 128 $ key1 [127:0] $end
$var reg 128 % key2 [127:0] $end
$var reg 1 & rst $end
$var reg 1 ' start $end
$scope module DUT $end
$var wire 1 # clk $end
$var wire 1 & rst $end
$var wire 1 ' start $end
$var wire 1 ( puf_valid2 $end
$var wire 1 ) puf_valid1 $end
$var wire 64 * puf_resp2 [63:0] $end
$var wire 64 + puf_resp1 [63:0] $end
$var parameter 3 , COMBINE $end
$var parameter 3 - IDLE $end
$var parameter 3 . PUF1_EN $end
$var parameter 3 / PUF2_EN $end
$var parameter 3 0 WAIT1 $end
$var parameter 3 1 WAIT2 $end
$var reg 128 2 device_key [127:0] $end
$var reg 1 ! key_ready $end
$var reg 1 3 puf_en1 $end
$var reg 1 4 puf_en2 $end
$var reg 3 5 state [2:0] $end
$scope module PUF1 $end
$var wire 8 6 challenge [7:0] $end
$var wire 1 # clk $end
$var wire 1 3 enable $end
$var wire 1 & rst $end
$var parameter 2 7 DONE $end
$var parameter 2 8 IDLE $end
$var parameter 2 9 PROCESS $end
$var parameter 2 : SAMPLE $end
$var reg 64 ; chip_id [63:0] $end
$var reg 4 < count [3:0] $end
$var reg 64 = raw_bits [63:0] $end
$var reg 64 > response [63:0] $end
$var reg 2 ? state [1:0] $end
$var reg 1 ) valid $end
$scope function puf_response $end
$var reg 8 @ challenge [7:0] $end
$var reg 64 A resp [63:0] $end
$var reg 64 B uid [63:0] $end
$var integer 32 C i [31:0] $end
$upscope $end
$upscope $end
$scope module PUF2 $end
$var wire 8 D challenge [7:0] $end
$var wire 1 # clk $end
$var wire 1 4 enable $end
$var wire 1 & rst $end
$var parameter 2 E DONE $end
$var parameter 2 F IDLE $end
$var parameter 2 G PROCESS $end
$var parameter 2 H SAMPLE $end
$var reg 64 I chip_id [63:0] $end
$var reg 4 J count [3:0] $end
$var reg 64 K raw_bits [63:0] $end
$var reg 64 L response [63:0] $end
$var reg 2 M state [1:0] $end
$var reg 1 ( valid $end
$scope function puf_response $end
$var reg 8 N challenge [7:0] $end
$var reg 64 O resp [63:0] $end
$var reg 64 P uid [63:0] $end
$var integer 32 Q i [31:0] $end
$upscope $end
$upscope $end
$upscope $end
$upscope $end
$enddefinitions $end
$comment Show the parameter values. $end
$dumpall
b1 H
b10 G
b0 F
b11 E
b1 :
b10 9
b0 8
b11 7
b100 1
b10 0
b11 /
b1 .
b0 -
b101 ,
$end
#0
$dumpvars
bx Q
bx P
bx O
bx N
b0 M
b0 L
b0 K
b0 J
b1101111010101101101111101110111111001010111111101011101010111110 I
b1011010 D
bx C
bx B
bx A
bx @
b0 ?
b0 >
b0 =
b0 <
b1101111010101101101111101110111111001010111111101011101010111110 ;
b10100101 6
b0 5
04
03
b0 2
b0 +
b0 *
0)
0(
0'
1&
bx %
bx $
0#
b0 "
0!
$end
#5
1#
#10
0#
#15
1#
#20
0#
#25
1#
#30
0#
0&
#35
1#
#40
0#
#45
1#
#50
0#
1'
#55
b1 5
13
1#
#60
0#
0'
#65
b10 5
03
b1 ?
1#
#70
0#
#75
b1 <
b1101111010101101101111101110111111001010111111101011101010111110 =
b1000 C
b1101111010101101101111101110111111001010111111101011101010111110 A
b10100101 @
b1101111010101101101111101110111111001010111111101011101010111110 B
1#
#80
0#
#85
b10 <
b1101111010101101101111101110111111001010111111101011101010111110 A
b1000 C
1#
#90
0#
#95
b11 <
b1101111010101101101111101110111111001010111111101011101010111110 A
b1000 C
1#
#100
0#
#105
b100 <
b1101111010101101101111101110111111001010111111101011101010111110 A
b1000 C
1#
#110
0#
#115
b101 <
b1101111010101101101111101110111111001010111111101011101010111110 A
b1000 C
1#
#120
0#
#125
b110 <
b1101111010101101101111101110111111001010111111101011101010111110 A
b1000 C
1#
#130
0#
#135
b111 <
b1101111010101101101111101110111111001010111111101011101010111110 A
b1000 C
1#
#140
0#
#145
b10 ?
b1000 <
b1101111010101101101111101110111111001010111111101011101010111110 A
b1000 C
1#
#150
0#
#155
b11 ?
b1101111010101101101111101110111100010100010100110000010001010001 +
b1101111010101101101111101110111100010100010100110000010001010001 >
1#
#160
0#
#165
b0 ?
1)
1#
#170
0#
#175
0)
b11 5
14
1#
#180
0#
#185
b100 5
04
b1 M
1#
#190
0#
#195
b1 J
b1101111010101101101111101110111111001010111111101011101010111110 K
b1000 Q
b1101111010101101101111101110111111001010111111101011101010111110 O
b1011010 N
b1101111010101101101111101110111111001010111111101011101010111110 P
1#
#200
0#
#205
b10 J
b1101111010101101101111101110111111001010111111101011101010111110 O
b1000 Q
1#
#210
0#
#215
b11 J
b1101111010101101101111101110111111001010111111101011101010111110 O
b1000 Q
1#
#220
0#
#225
b100 J
b1101111010101101101111101110111111001010111111101011101010111110 O
b1000 Q
1#
#230
0#
#235
b101 J
b1101111010101101101111101110111111001010111111101011101010111110 O
b1000 Q
1#
#240
0#
#245
b110 J
b1101111010101101101111101110111111001010111111101011101010111110 O
b1000 Q
1#
#250
0#
#255
b111 J
b1101111010101101101111101110111111001010111111101011101010111110 O
b1000 Q
1#
#260
0#
#265
b10 M
b1000 J
b1101111010101101101111101110111111001010111111101011101010111110 O
b1000 Q
1#
#270
0#
#275
b11 M
b1101111010101101101111101110111100010100010100110000010001010001 *
b1101111010101101101111101110111100010100010100110000010001010001 L
1#
#280
0#
#285
b0 M
1(
1#
#290
0#
#295
0(
b101 5
1#
#300
0#
#305
b11011110101011011011111011101111000101000101001100000100010100011101111010101101101111101110111100010100010100110000010001010001 $
b0 5
1!
b11011110101011011011111011101111000101000101001100000100010100011101111010101101101111101110111100010100010100110000010001010001 "
b11011110101011011011111011101111000101000101001100000100010100011101111010101101101111101110111100010100010100110000010001010001 2
1#
#310
0#
#315
0!
1#
#320
0#
#325
1#
#330
0#
#335
1#
#340
0#
#345
1#
#350
0#
#355
b1 5
13
1#
1'
#360
0#
#365
b10 5
03
b1 ?
b0 =
b0 <
1#
0'
#370
0#
#375
b1 <
b1101111010101101101111101110111111001010111111101011101010111110 =
b1101111010101101101111101110111111001010111111101011101010111110 A
b1000 C
1#
#380
0#
#385
b10 <
b1101111010101101101111101110111111001010111111101011101010111110 A
b1000 C
1#
#390
0#
#395
b11 <
b1101111010101101101111101110111111001010111111101011101010111110 A
b1000 C
1#
#400
0#
#405
b100 <
b1101111010101101101111101110111111001010111111101011101010111110 A
b1000 C
1#
#410
0#
#415
b101 <
b1101111010101101101111101110111111001010111111101011101010111110 A
b1000 C
1#
#420
0#
#425
b110 <
b1101111010101101101111101110111111001010111111101011101010111110 A
b1000 C
1#
#430
0#
#435
b111 <
b1101111010101101101111101110111111001010111111101011101010111110 A
b1000 C
1#
#440
0#
#445
b10 ?
b1000 <
b1101111010101101101111101110111111001010111111101011101010111110 A
b1000 C
1#
#450
0#
#455
b11 ?
1#
#460
0#
#465
b0 ?
1)
1#
#470
0#
#475
0)
b11 5
14
1#
#480
0#
#485
b100 5
04
b1 M
b0 K
b0 J
1#
#490
0#
#495
b1 J
b1101111010101101101111101110111111001010111111101011101010111110 K
b1101111010101101101111101110111111001010111111101011101010111110 O
b1000 Q
1#
#500
0#
#505
b10 J
b1101111010101101101111101110111111001010111111101011101010111110 O
b1000 Q
1#
#510
0#
#515
b11 J
b1101111010101101101111101110111111001010111111101011101010111110 O
b1000 Q
1#
#520
0#
#525
b100 J
b1101111010101101101111101110111111001010111111101011101010111110 O
b1000 Q
1#
#530
0#
#535
b101 J
b1101111010101101101111101110111111001010111111101011101010111110 O
b1000 Q
1#
#540
0#
#545
b110 J
b1101111010101101101111101110111111001010111111101011101010111110 O
b1000 Q
1#
#550
0#
#555
b111 J
b1101111010101101101111101110111111001010111111101011101010111110 O
b1000 Q
1#
#560
0#
#565
b10 M
b1000 J
b1101111010101101101111101110111111001010111111101011101010111110 O
b1000 Q
1#
#570
0#
#575
b11 M
1#
#580
0#
#585
b0 M
1(
1#
#590
0#
#595
0(
b101 5
1#
#600
0#
#605
b11011110101011011011111011101111000101000101001100000100010100011101111010101101101111101110111100010100010100110000010001010001 %
b0 5
1!
1#
#610
0#
#615
0!
1#
