day7/reg_file.v
module reg_file(
    input  wire        clk,
    input  wire        rst,
    input  wire        wr_en,
    input  wire [2:0]  wr_addr,
    input  wire [7:0]  wr_data,
    input  wire [2:0]  rd_addr1,
    input  wire [2:0]  rd_addr2,
    output wire [7:0]  rd_data1,
    output wire [7:0]  rd_data2
);
    // 8 registers, har ek 8-bit
    reg [7:0] registers [0:7];
    integer i;

    // Write operation
    always @(posedge clk or posedge rst) begin
        if (rst) begin
            for (i=0; i<8; i=i+1)
                registers[i] <= 8'b0;
        end
        else if (wr_en) begin
            registers[wr_addr] <= wr_data;
        end
    end

    // Read operation
    assign rd_data1 = registers[rd_addr1];
    assign rd_data2 = registers[rd_addr2];

endmodule

day4/reg_file_tb.v
module reg_file_tb;

    reg        clk, rst, wr_en;
    reg  [2:0] wr_addr, rd_addr1, rd_addr2;
    reg  [7:0] wr_data;
    wire [7:0] rd_data1, rd_data2;

    reg_file uut (
        .clk(clk), .rst(rst),
        .wr_en(wr_en), .wr_addr(wr_addr),
        .wr_data(wr_data),
        .rd_addr1(rd_addr1), .rd_addr2(rd_addr2),
        .rd_data1(rd_data1), .rd_data2(rd_data2)
    );

    initial clk = 0;
    always #5 clk = ~clk;

    initial begin
        $dumpfile("reg_file.vcd");
        $dumpvars(0, reg_file_tb);

        rst=1; wr_en=0; #20;
        rst=0;

        wr_en=1; wr_addr=3'd0; wr_data=8'd42; #10;
        rd_addr1=3'd0; #1;
        if(rd_data1==8'd42)
            $display("✓ R0 = 42 PASS");
        else
            $display("✗ R0 FAIL");

        wr_addr=3'd1; wr_data=8'd100; #10;
        wr_addr=3'd2; wr_data=8'd255; #10;

        wr_en=0;
        rd_addr1=3'd1; rd_addr2=3'd2; #10;
        if(rd_data1==8'd100 && rd_data2==8'd255)
            $display("✓ R1=100, R2=255 — Dual Read PASS");
        else
            $display("✗ Dual Read FAIL");

        rst=1; #20; rst=0;
        rd_addr1=3'd0; #10;
        if(rd_data1==8'd0)
            $display("✓ Reset — R0=0 PASS");
        else
            $display("✗ Reset FAIL");

        $display("Day 4 Complete! Register File working!");
        $finish;
    end

endmodule

day4/reg_file.vcd
$date
	Mon Jul 27 18:44:37 2026
$end
$version
	Icarus Verilog
$end
$timescale
	1s
$end
$scope module reg_file_tb $end
$var wire 8 ! rd_data2 [7:0] $end
$var wire 8 " rd_data1 [7:0] $end
$var reg 1 # clk $end
$var reg 3 $ rd_addr1 [2:0] $end
$var reg 3 % rd_addr2 [2:0] $end
$var reg 1 & rst $end
$var reg 3 ' wr_addr [2:0] $end
$var reg 8 ( wr_data [7:0] $end
$var reg 1 ) wr_en $end
$scope module uut $end
$var wire 1 # clk $end
$var wire 3 * rd_addr1 [2:0] $end
$var wire 3 + rd_addr2 [2:0] $end
$var wire 8 , rd_data1 [7:0] $end
$var wire 8 - rd_data2 [7:0] $end
$var wire 1 & rst $end
$var wire 3 . wr_addr [2:0] $end
$var wire 8 / wr_data [7:0] $end
$var wire 1 ) wr_en $end
$var integer 32 0 i [31:0] $end
$upscope $end
$upscope $end
$enddefinitions $end
$comment Show the parameter values. $end
$dumpall
$end
#0
$dumpvars
b1000 0
bx /
bx .
bx -
bx ,
bx +
bx *
0)
bx (
bx '
1&
bx %
bx $
0#
bx "
bx !
$end
#5
b1000 0
1#
#10
0#
#15
b1000 0
1#
#20
0#
b101010 (
b101010 /
b0 '
b0 .
1)
0&
#25
1#
#30
0#
b101010 "
b101010 ,
b0 $
b0 *
#31
b1100100 (
b1100100 /
b1 '
b1 .
#35
1#
#40
0#
#41
b11111111 (
b11111111 /
b10 '
b10 .
#45
1#
#50
0#
#51
b11111111 !
b11111111 -
b10 %
b10 +
b1100100 "
b1100100 ,
b1 $
b1 *
0)
#55
1#
#60
0#
#61
b0 !
b0 -
b0 "
b0 ,
b1000 0
1&
#65
b1000 0
1#
#70
0#
#75
b1000 0
1#
#80
0#
#81
b0 $
b0 *
0&
