day14/interrupt_ctrl.v
module interrupt_ctrl(
    input  wire        clk,
    input  wire        rst,
    // Interrupt sources
    input  wire        tamper_irq,
    input  wire        timer_irq,
    input  wire        uart_irq,
    input  wire        spi_irq,
    // CPU interface
    input  wire [3:0]  irq_mask,
    input  wire        irq_ack,
    // Outputs
    output reg         irq_out,
    output reg  [3:0]  irq_id,
    output reg         keys_erase
);
    parameter IDLE    = 2'd0;
    parameter PENDING = 2'd1;
    parameter SERVING = 2'd2;

    reg [1:0] state;
    reg [3:0] irq_reg;

    always @(posedge clk or posedge rst) begin
        if (rst) begin
            state      <= IDLE;
            irq_out    <= 0;
            irq_id     <= 0;
            keys_erase <= 0;
            irq_reg    <= 0;
        end
        else begin
            // Latch interrupts
            irq_reg[0] <= tamper_irq;
            irq_reg[1] <= timer_irq;
            irq_reg[2] <= uart_irq;
            irq_reg[3] <= spi_irq;

            case (state)
                IDLE: begin
                    irq_out    <= 0;
                    keys_erase <= 0;

                    // Priority: tamper > timer > uart > spi
                    if (irq_reg[0] & ~irq_mask[0]) begin
                        irq_id  <= 4'd1;
                        irq_out <= 1;
                        // TAMPER — keys erase karo!
                        keys_erase <= 1;
                        state   <= SERVING;
                    end
                    else if (irq_reg[1] & ~irq_mask[1]) begin
                        irq_id  <= 4'd2;
                        irq_out <= 1;
                        state   <= SERVING;
                    end
                    else if (irq_reg[2] & ~irq_mask[2]) begin
                        irq_id  <= 4'd3;
                        irq_out <= 1;
                        state   <= SERVING;
                    end
                    else if (irq_reg[3] & ~irq_mask[3]) begin
                        irq_id  <= 4'd4;
                        irq_out <= 1;
                        state   <= SERVING;
                    end
                end

                SERVING: begin
                    if (irq_ack) begin
                        irq_out    <= 0;
                        keys_erase <= 0;
                        state      <= IDLE;
                    end
                end
            endcase
        end
    end
endmodule

day13/interrupt_tb.v
module interrupt_tb;

    reg        clk, rst;
    reg        tamper_irq, timer_irq;
    reg        uart_irq, spi_irq;
    reg  [3:0] irq_mask;
    reg        irq_ack;
    wire       irq_out;
    wire [3:0] irq_id;
    wire       keys_erase;

    interrupt_ctrl DUT (
        .clk(clk), .rst(rst),
        .tamper_irq(tamper_irq),
        .timer_irq(timer_irq),
        .uart_irq(uart_irq),
        .spi_irq(spi_irq),
        .irq_mask(irq_mask),
        .irq_ack(irq_ack),
        .irq_out(irq_out),
        .irq_id(irq_id),
        .keys_erase(keys_erase)
    );

    initial clk = 0;
    always #5 clk = ~clk;

    initial begin
        $dumpfile("interrupt.vcd");
        $dumpvars(0, interrupt_tb);

        rst=1;
        tamper_irq=0; timer_irq=0;
        uart_irq=0;   spi_irq=0;
        irq_mask=4'b0000;
        irq_ack=0;
        #30; rst=0; #20;

        $display("================================");
        $display("  INTERRUPT CONTROLLER TEST    ");
        $display("================================");

        // Test 1: Timer
        $display("--- Test 1: Timer IRQ ---");
        timer_irq=1; #30; timer_irq=0; #20;
        if(irq_out && irq_id==4'd2)
            $display("PASS: Timer IRQ ID=%0d", irq_id);
        else
            $display("FAIL: Timer IRQ");
        irq_ack=1; #10; irq_ack=0; #20;

        // Test 2: UART
        $display("--- Test 2: UART IRQ ---");
        uart_irq=1; #30; uart_irq=0; #20;
        if(irq_out && irq_id==4'd3)
            $display("PASS: UART IRQ ID=%0d", irq_id);
        else
            $display("FAIL: UART IRQ");
        irq_ack=1; #10; irq_ack=0; #20;

        // Test 3: TAMPER
        $display("--- Test 3: TAMPER IRQ ---");
        tamper_irq=1; #30; tamper_irq=0; #20;
        if(irq_out && keys_erase==1)
            $display("PASS: TAMPER Keys Erased ID=%0d", irq_id);
        else
            $display("FAIL: TAMPER IRQ");
        irq_ack=1; #10; irq_ack=0; #20;

        // Test 4: Priority
        $display("--- Test 4: Priority ---");
        timer_irq=1; tamper_irq=1; #30;
        timer_irq=0; tamper_irq=0; #20;
        if(irq_id==4'd1 && keys_erase==1)
            $display("PASS: Tamper wins priority");
        else
            $display("FAIL: Priority");
        irq_ack=1; #10; irq_ack=0; #20;

        $display("================================");
        $display("Day 13 Complete! IRQ working!");
        $display("================================");
        $finish;
    end

endmodule

day13/interrupt.vcd
$date
	Tue Jul 28 08:30:04 2026
$end
$version
	Icarus Verilog
$end
$timescale
	1s
$end
$scope module interrupt_tb $end
$var wire 1 ! keys_erase $end
$var wire 1 " irq_out $end
$var wire 4 # irq_id [3:0] $end
$var reg 1 $ clk $end
$var reg 1 % irq_ack $end
$var reg 4 & irq_mask [3:0] $end
$var reg 1 ' rst $end
$var reg 1 ( spi_irq $end
$var reg 1 ) tamper_irq $end
$var reg 1 * timer_irq $end
$var reg 1 + uart_irq $end
$scope module DUT $end
$var wire 1 $ clk $end
$var wire 1 % irq_ack $end
$var wire 4 , irq_mask [3:0] $end
$var wire 1 ' rst $end
$var wire 1 ( spi_irq $end
$var wire 1 ) tamper_irq $end
$var wire 1 * timer_irq $end
$var wire 1 + uart_irq $end
$var parameter 2 - IDLE $end
$var parameter 2 . PENDING $end
$var parameter 2 / SERVING $end
$var reg 4 0 irq_id [3:0] $end
$var reg 1 " irq_out $end
$var reg 4 1 irq_reg [3:0] $end
$var reg 1 ! keys_erase $end
$var reg 2 2 state [1:0] $end
$upscope $end
$upscope $end
$enddefinitions $end
$comment Show the parameter values. $end
$dumpall
b10 /
b1 .
b0 -
$end
#0
$dumpvars
b0 2
b0 1
b0 0
b0 ,
0+
0*
0)
0(
1'
b0 &
0%
0$
b0 #
0"
0!
$end
#5
1$
#10
0$
#15
1$
#20
0$
#25
1$
#30
0$
0'
#35
1$
#40
0$
#45
1$
#50
0$
1*
#55
b10 1
1$
#60
0$
#65
b10 2
1"
b10 #
b10 0
1$
#70
0$
#75
1$
#80
0$
0*
#85
b0 1
1$
#90
0$
#95
1$
#100
0$
1%
#105
b0 2
0"
1$
#110
0$
0%
#115
1$
#120
0$
#125
1$
#130
0$
1+
#135
b100 1
1$
#140
0$
#145
b10 2
1"
b11 #
b11 0
1$
#150
0$
#155
1$
#160
0$
0+
#165
b0 1
1$
#170
0$
#175
1$
#180
0$
1%
#185
b0 2
0"
1$
#190
0$
0%
#195
1$
#200
0$
#205
1$
#210
0$
1)
#215
b1 1
1$
#220
0$
#225
b10 2
1!
1"
b1 #
b1 0
1$
#230
0$
#235
1$
#240
0$
0)
#245
b0 1
1$
#250
0$
#255
1$
#260
0$
1%
#265
b0 2
0!
0"
1$
#270
0$
0%
#275
1$
#280
0$
#285
1$
#290
0$
1)
1*
#295
b11 1
1$
#300
0$
#305
b10 2
1!
1"
1$
#310
0$
#315
1$
#320
0$
0)
0*
#325
b0 1
1$
#330
0$
#335
1$
#340
0$
1%
#345
b0 2
0!
0"
1$
#350
0$
0%
