day10/spi_slave.v
module spi_slave(
    input  wire       clk,
    input  wire       rst,
    input  wire       sclk,
    input  wire       cs_n,
    input  wire       mosi,
    output reg        miso,
    output reg  [7:0] rx_data,
    output reg        valid
);
    reg [2:0] bit_cnt;
    reg [7:0] shift_reg;
    reg       sclk_prev;

    always @(posedge clk or posedge rst) begin
        if (rst) begin
            bit_cnt   <= 7;
            shift_reg <= 0;
            rx_data   <= 0;
            valid     <= 0;
            miso      <= 0;
            sclk_prev <= 0;
        end
        else begin
            valid     <= 0;
            sclk_prev <= sclk;

            if (!cs_n) begin
                // Rising edge detect
                if (sclk && !sclk_prev) begin
                    shift_reg <= {shift_reg[6:0], mosi};
                    miso      <= shift_reg[7];
                    if (bit_cnt == 0) begin
                        rx_data <= {shift_reg[6:0], mosi};
                        valid   <= 1;
                        bit_cnt <= 7;
                    end else
                        bit_cnt <= bit_cnt - 1;
                end
            end else begin
                bit_cnt <= 7;
            end
        end
    end
endmodule

day10/spi_master.v
module spi_master(
    input  wire       clk,
    input  wire       rst,
    input  wire       start,
    input  wire [7:0] mosi_data,
    output reg        sclk,
    output reg        cs_n,
    output reg        mosi,
    input  wire       miso,
    output reg  [7:0] miso_data,
    output reg        done
);
    parameter IDLE     = 2'd0;
    parameter TRANSFER = 2'd1;
    parameter FINISH   = 2'd2;

    reg [1:0] state;
    reg [2:0] bit_cnt;
    reg [7:0] shift_out;
    reg [7:0] shift_in;

    always @(posedge clk or posedge rst) begin
        if (rst) begin
            state     <= IDLE;
            sclk      <= 0;
            cs_n      <= 1;
            mosi      <= 0;
            miso_data <= 0;
            done      <= 0;
            bit_cnt   <= 7;
            shift_out <= 0;
            shift_in  <= 0;
        end
        else begin
            case (state)
                IDLE: begin
                    sclk <= 0;
                    cs_n <= 1;
                    done <= 0;
                    if (start) begin
                        shift_out <= mosi_data;
                        bit_cnt   <= 7;
                        cs_n      <= 0;
                        state     <= TRANSFER;
                    end
                end

                TRANSFER: begin
                    sclk <= ~sclk;
                    if (!sclk) begin
                        // Rising edge — data sample
                        mosi <= shift_out[bit_cnt];
                        shift_in <= {shift_in[6:0], miso};
                    end else begin
                        // Falling edge — next bit
                        if (bit_cnt == 0) begin
                            state <= FINISH;
                        end else
                            bit_cnt <= bit_cnt - 1;
                    end
                end

                FINISH: begin
                    cs_n      <= 1;
                    sclk      <= 0;
                    miso_data <= shift_in;
                    done      <= 1;
                    state     <= IDLE;
                end
            endcase
        end
    end
endmodule

day10/spi_tb.v
module spi_tb;

    reg        clk, rst, start;
    reg  [7:0] mosi_data;
    wire       sclk, cs_n, mosi;
    wire [7:0] miso_data;
    wire       done;
    wire       miso;
    wire [7:0] slave_rx;
    wire       slave_valid;

    spi_master MASTER (
        .clk(clk), .rst(rst),
        .start(start),
        .mosi_data(mosi_data),
        .sclk(sclk), .cs_n(cs_n),
        .mosi(mosi), .miso(miso),
        .miso_data(miso_data),
        .done(done)
    );

    spi_slave SLAVE (
        .clk(clk), .rst(rst),
        .sclk(sclk), .cs_n(cs_n),
        .mosi(mosi), .miso(miso),
        .rx_data(slave_rx),
        .valid(slave_valid)
    );

    initial clk = 0;
    always #5 clk = ~clk;

    always @(posedge slave_valid)
        $display("✓ Slave received=%0d PASS", slave_rx);

    always @(posedge done)
        $display("✓ Master done | MISO data=%0d", miso_data);

    initial begin
        $dumpfile("spi.vcd");
        $dumpvars(0, spi_tb);

        rst=1; start=0; mosi_data=0; #30;
        rst=0; #20;

        $display("================================");
        $display("   SPI MASTER → SLAVE TEST     ");
        $display("================================");

        // Test 1: 170 bhejo (10101010)
        mosi_data=8'd170; start=1; #10; start=0;
        #500;

        // Test 2: 85 bhejo (01010101)
        mosi_data=8'd85; start=1; #10; start=0;
        #500;

        // Test 3: 255 bhejo (11111111)
        mosi_data=8'd255; start=1; #10; start=0;
        #500;

        $display("================================");
        $display("Day 10 Complete! SPI working!");
        $display("Master + Slave verified!");
        $display("================================");
        $finish;
    end

endmodule

day10/spi.vcd
$date
	Mon Jul 27 18:57:55 2026
$end
$version
	Icarus Verilog
$end
$timescale
	1s
$end
$scope module spi_tb $end
$var wire 1 ! slave_valid $end
$var wire 8 " slave_rx [7:0] $end
$var wire 1 # sclk $end
$var wire 1 $ mosi $end
$var wire 8 % miso_data [7:0] $end
$var wire 1 & miso $end
$var wire 1 ' done $end
$var wire 1 ( cs_n $end
$var reg 1 ) clk $end
$var reg 8 * mosi_data [7:0] $end
$var reg 1 + rst $end
$var reg 1 , start $end
$scope module MASTER $end
$var wire 1 ) clk $end
$var wire 8 - mosi_data [7:0] $end
$var wire 1 + rst $end
$var wire 1 , start $end
$var wire 1 & miso $end
$var parameter 2 . FINISH $end
$var parameter 2 / IDLE $end
$var parameter 2 0 TRANSFER $end
$var reg 3 1 bit_cnt [2:0] $end
$var reg 1 ( cs_n $end
$var reg 1 ' done $end
$var reg 8 2 miso_data [7:0] $end
$var reg 1 $ mosi $end
$var reg 1 # sclk $end
$var reg 8 3 shift_in [7:0] $end
$var reg 8 4 shift_out [7:0] $end
$var reg 2 5 state [1:0] $end
$upscope $end
$scope module SLAVE $end
$var wire 1 ) clk $end
$var wire 1 ( cs_n $end
$var wire 1 $ mosi $end
$var wire 1 + rst $end
$var wire 1 # sclk $end
$var reg 3 6 bit_cnt [2:0] $end
$var reg 1 & miso $end
$var reg 8 7 rx_data [7:0] $end
$var reg 1 8 sclk_prev $end
$var reg 8 9 shift_reg [7:0] $end
$var reg 1 ! valid $end
$upscope $end
$upscope $end
$enddefinitions $end
$comment Show the parameter values. $end
$dumpall
b1 0
b0 /
b10 .
$end
#0
$dumpvars
b0 9
08
b0 7
b111 6
b0 5
b0 4
b0 3
b0 2
b111 1
b0 -
0,
1+
b0 *
0)
1(
0'
0&
b0 %
0$
0#
b0 "
0!
$end
#5
1)
#10
0)
#15
1)
#20
0)
#25
1)
#30
0)
0+
#35
1)
#40
0)
#45
1)
#50
0)
1,
b10101010 *
b10101010 -
#55
b1 5
0(
b10101010 4
1)
#60
0)
0,
#65
1$
1#
1)
#70
0)
#75
b110 1
0#
b110 6
b1 9
18
1)
#80
0)
#85
08
0$
1#
1)
#90
0)
#95
b101 1
0#
b101 6
b10 9
18
1)
#100
0)
#105
08
1$
1#
1)
#110
0)
#115
b100 1
0#
b100 6
b101 9
18
1)
#120
0)
#125
08
0$
1#
1)
#130
0)
#135
b11 1
0#
b11 6
b1010 9
18
1)
#140
0)
#145
08
1$
1#
1)
#150
0)
#155
b10 1
0#
b10 6
b10101 9
18
1)
#160
0)
#165
08
0$
1#
1)
#170
0)
#175
b1 1
0#
b1 6
b101010 9
18
1)
#180
0)
#185
08
1$
1#
1)
#190
0)
#195
b0 1
0#
b0 6
b1010101 9
18
1)
#200
0)
#205
08
0$
1#
1)
#210
0)
#215
b10 5
0#
b111 6
1!
b10101010 "
b10101010 7
b10101010 9
18
1)
#220
0)
#225
08
0!
b0 5
1'
1(
1)
#230
0)
#235
0'
1)
