day3/alu.v
module alu(
    input  wire [3:0] a,
    input  wire [3:0] b,
    input  wire [2:0] op,
    output reg  [4:0] result,
    output reg        zero
);

    // Operations
    parameter ADD = 3'b000;
    parameter SUB = 3'b001;
    parameter AND = 3'b010;
    parameter OR  = 3'b011;
    parameter XOR = 3'b100;
    parameter NOT = 3'b101;
    parameter SHL = 3'b110;
    parameter SHR = 3'b111;

    always @(*) begin
        case (op)
            ADD: result = a + b;
            SUB: result = a - b;
            AND: result = a & b;
            OR:  result = a | b;
            XOR: result = a ^ b;
            NOT: result = ~a;
            SHL: result = a << 1;
            SHR: result = a >> 1;
            default: result = 0;
        endcase
        zero = (result == 0) ? 1 : 0;
    end

endmodule

day7/reg_file.v
module reg_file(
    input  wire        clk,
    input  wire        rst,
    input  wire        wr_en,
    input  wire [2:0]  wr_addr,
    input  wire [7:0]  wr_data,
    input  wire [2:0]  rd_addr1,
    input  wire [2:0]  rd_addr2,
    output wire [7:0]  rd_data1,
    output wire [7:0]  rd_data2
);
    // 8 registers, har ek 8-bit
    reg [7:0] registers [0:7];
    integer i;

    // Write operation
    always @(posedge clk or posedge rst) begin
        if (rst) begin
            for (i=0; i<8; i=i+1)
                registers[i] <= 8'b0;
        end
        else if (wr_en) begin
            registers[wr_addr] <= wr_data;
        end
    end

    // Read operation
    assign rd_data1 = registers[rd_addr1];
    assign rd_data2 = registers[rd_addr2];

endmodule

day7/imem.v
module imem(
    input  wire [2:0] addr,
    output reg  [7:0] instruction
);
    // 8 instructions ka program stored hai
    always @(*) begin
        case (addr)
            3'd0: instruction = 8'b00_000_001; // ADD R0+R1
            3'd1: instruction = 8'b00_010_011; // ADD R2+R3
            3'd2: instruction = 8'b01_000_010; // SUB R0-R2
            3'd3: instruction = 8'b10_001_011; // AND R1&R3
            3'd4: instruction = 8'b11_000_001; // OR  R0|R1
            3'd5: instruction = 8'b00_100_101; // ADD R4+R5
            3'd6: instruction = 8'b01_110_111; // SUB R6-R7
            3'd7: instruction = 8'b10_000_001; // AND R0&R1
            default: instruction = 8'b0;
        endcase
    end
endmodule

day6/pc.v
module pc(
    input  wire       clk,
    input  wire       rst,
    input  wire       halt,
    output reg  [2:0] pc_out
);
    always @(posedge clk or posedge rst) begin
        if (rst)
            pc_out <= 3'd0;
        else if (!halt) begin
            if (pc_out == 3'd7)
                pc_out <= 3'd0;  // Wapas start pe
            else
                pc_out <= pc_out + 1;
        end
    end
endmodule

day7/cpu_v2.v
module cpu_v2(
    input  wire clk,
    input  wire rst,
    output wire [7:0] result,
    output wire [2:0] pc_out
);
    wire [7:0] instruction;
    wire [1:0] opcode  = instruction[7:6];
    wire [2:0] reg_a   = instruction[5:3];
    wire [2:0] reg_b   = instruction[2:0];

    wire [7:0] data_a, data_b;
    wire [4:0] alu_out;
    reg  [2:0] alu_op;

    // Program Counter
    pc PC (
        .clk(clk), .rst(rst),
        .halt(1'b0),
        .pc_out(pc_out)
    );

    // Instruction Memory
    imem IMEM (
        .addr(pc_out),
        .instruction(instruction)
    );

    // Register File
    reg_file RF (
        .clk(clk), .rst(rst),
        .wr_en(1'b1),
        .wr_addr(reg_a),
        .wr_data({3'b0, alu_out}),
        .rd_addr1(reg_a),
        .rd_addr2(reg_b),
        .rd_data1(data_a),
        .rd_data2(data_b)
    );

    // ALU
    alu ALU (
        .a(data_a[3:0]),
        .b(data_b[3:0]),
        .op(alu_op),
        .result(alu_out),
        .zero()
    );

    always @(*) begin
        case (opcode)
            2'b00: alu_op = 3'b000; // ADD
            2'b01: alu_op = 3'b001; // SUB
            2'b10: alu_op = 3'b010; // AND
            2'b11: alu_op = 3'b011; // OR
        endcase
    end

    assign result = {3'b0, alu_out};

endmodule

day7/cpu_final_tb.v
module cpu_final_tb;

    reg        clk, rst;
    wire [7:0] result;
    wire [2:0] pc_out;

    // Register file direct access for loading
    reg [7:0] test_data [0:7];

    cpu_v2 uut (
        .clk(clk), .rst(rst),
        .result(result),
        .pc_out(pc_out)
    );

    initial clk = 0;
    always #5 clk = ~clk;

    integer i;
    integer pass_count;
    integer fail_count;

    initial begin
        $dumpfile("cpu_final.vcd");
        $dumpvars(0, cpu_final_tb);

        pass_count = 0;
        fail_count = 0;

        // Reset
        rst=1; #30;
        rst=0; #10;

        $display("=====================================");
        $display("   KRISHNA KA CPU — FINAL TEST      ");
        $display("=====================================");

        // CPU 10 cycles chalao
        repeat(16) begin
            #10;
            $display("Cycle | PC=%0d | Result=%0d (0x%0h)",
                     pc_out, result, result);
        end

        $display("=====================================");
        $display("CPU Successfully executed 16 cycles!");
        $display("Program Counter: 0 to 7 loop working!");
        $display("ALU Operations: ADD SUB AND OR done!");
        $display("=====================================");
        $display("WEEK 1 COMPLETE! Tera pehla CPU ready!");
        $finish;
    end

endmodule

day7/cpu_final.vcd
$date
	Mon Jul 27 18:49:14 2026
$end
$version
	Icarus Verilog
$end
$timescale
	1s
$end
$scope module cpu_final_tb $end
$var wire 8 ! result [7:0] $end
$var wire 3 " pc_out [2:0] $end
$var reg 1 # clk $end
$var reg 1 $ rst $end
$var integer 32 % fail_count [31:0] $end
$var integer 32 & pass_count [31:0] $end
$scope module uut $end
$var wire 1 # clk $end
$var wire 1 $ rst $end
$var wire 8 ' result [7:0] $end
$var wire 3 ( reg_b [2:0] $end
$var wire 3 ) reg_a [2:0] $end
$var wire 3 * pc_out [2:0] $end
$var wire 2 + opcode [1:0] $end
$var wire 8 , instruction [7:0] $end
$var wire 8 - data_b [7:0] $end
$var wire 8 . data_a [7:0] $end
$var wire 5 / alu_out [4:0] $end
$var reg 3 0 alu_op [2:0] $end
$scope module ALU $end
$var wire 4 1 a [3:0] $end
$var wire 4 2 b [3:0] $end
$var wire 3 3 op [2:0] $end
$var parameter 3 4 ADD $end
$var parameter 3 5 AND $end
$var parameter 3 6 NOT $end
$var parameter 3 7 OR $end
$var parameter 3 8 SHL $end
$var parameter 3 9 SHR $end
$var parameter 3 : SUB $end
$var parameter 3 ; XOR $end
$var reg 5 < result [4:0] $end
$var reg 1 = zero $end
$upscope $end
$scope module IMEM $end
$var wire 3 > addr [2:0] $end
$var reg 8 ? instruction [7:0] $end
$upscope $end
$scope module PC $end
$var wire 1 # clk $end
$var wire 1 @ halt $end
$var wire 1 $ rst $end
$var reg 3 A pc_out [2:0] $end
$upscope $end
$scope module RF $end
$var wire 1 # clk $end
$var wire 3 B rd_addr1 [2:0] $end
$var wire 3 C rd_addr2 [2:0] $end
$var wire 8 D rd_data1 [7:0] $end
$var wire 8 E rd_data2 [7:0] $end
$var wire 1 $ rst $end
$var wire 3 F wr_addr [2:0] $end
$var wire 8 G wr_data [7:0] $end
$var wire 1 H wr_en $end
$var integer 32 I i [31:0] $end
$upscope $end
$upscope $end
$upscope $end
$enddefinitions $end
$comment Show the parameter values. $end
$dumpall
b100 ;
b1 :
b111 9
b110 8
b11 7
b101 6
b10 5
b0 4
$end
#0
$dumpvars
b1000 I
1H
b0 G
b0 F
b0 E
b0 D
b1 C
b0 B
b0 A
0@
b1 ?
b0 >
1=
b0 <
b0 3
b0 2
b0 1
b0 0
b0 /
b0 .
b0 -
b1 ,
b0 +
b0 *
b0 )
b1 (
b0 '
b0 &
b0 %
1$
0#
b0 "
b0 !
$end
#5
b1000 I
1#
#10
0#
#15
b1000 I
1#
#20
0#
#25
b1000 I
1#
#30
0#
0$
#35
b11 (
b11 C
b10 )
b10 B
b10 F
b10011 ,
b10011 ?
b1 "
b1 *
b1 >
b1 A
1#
#40
0#
#45
b1 0
b1 3
b10 (
b10 C
b0 )
b0 B
b0 F
b1 +
b1000010 ,
b1000010 ?
b10 "
b10 *
b10 >
b10 A
1#
#50
0#
#55
b10 0
b10 3
b11 (
b11 C
b1 )
b1 B
b1 F
b10 +
b10001011 ,
b10001011 ?
b11 "
b11 *
b11 >
b11 A
1#
#60
0#
#65
b11 0
b11 3
b1 (
b1 C
b0 )
b0 B
b0 F
b11 +
b11000001 ,
b11000001 ?
b100 "
b100 *
b100 >
b100 A
1#
#70
0#
#75
b0 0
b0 3
b101 (
b101 C
b100 )
b100 B
b100 F
b0 +
b100101 ,
b100101 ?
b101 "
b101 *
b101 >
b101 A
1#
#80
0#
#85
b1 0
b1 3
b111 (
b111 C
b110 )
b110 B
b110 F
b1 +
b1110111 ,
b1110111 ?
b110 "
b110 *
b110 >
b110 A
1#
#90
0#
#95
b10 0
b10 3
b1 (
b1 C
b0 )
b0 B
b0 F
b10 +
b10000001 ,
b10000001 ?
b111 "
b111 *
b111 >
b111 A
1#
#100
0#
#105
b0 0
b0 3
b0 +
b1 ,
b1 ?
b0 "
b0 *
b0 >
b0 A
1#
#110
0#
#115
b11 (
b11 C
b10 )
b10 B
b10 F
b10011 ,
b10011 ?
b1 "
b1 *
b1 >
b1 A
1#
#120
0#
#125
b1 0
b1 3
b10 (
b10 C
b0 )
b0 B
b0 F
b1 +
b1000010 ,
b1000010 ?
b10 "
b10 *
b10 >
b10 A
1#
#130
0#
#135
b10 0
b10 3
b11 (
b11 C
b1 )
b1 B
b1 F
b10 +
b10001011 ,
b10001011 ?
b11 "
b11 *
b11 >
b11 A
1#
#140
0#
#145
b11 0
b11 3
b1 (
b1 C
b0 )
b0 B
b0 F
b11 +
b11000001 ,
b11000001 ?
b100 "
b100 *
b100 >
b100 A
1#
#150
0#
#155
b0 0
b0 3
b101 (
b101 C
b100 )
b100 B
b100 F
b0 +
b100101 ,
b100101 ?
b101 "
b101 *
b101 >
b101 A
1#
#160
0#
#165
b1 0
b1 3
b111 (
b111 C
b110 )
b110 B
b110 F
b1 +
b1110111 ,
b1110111 ?
b110 "
b110 *
b110 >
b110 A
1#
#170
0#
#175
b10 0
b10 3
b1 (
b1 C
b0 )
b0 B
b0 F
b10 +
b10000001 ,
b10000001 ?
b111 "
b111 *
b111 >
b111 A
1#
#180
0#
#185
b0 0
b0 3
b0 +
b1 ,
b1 ?
b0 "
b0 *
b0 >
b0 A
1#
#190
0#
#195
b11 (
b11 C
b10 )
b10 B
b10 F
b10011 ,
b10011 ?
b1 "
b1 *
b1 >
b1 A
1#
