laghu_npu/src/relu.v
// ReLU: negative numbers ko 0 kar deta hai, positive rehte hain
module relu (
    input  wire signed [31:0] data_in,
    output wire signed [31:0] data_out
);
    assign data_out = (data_in[31] == 1'b1) ? 32'sd0 : data_in;
endmodule

laghu_npu/src/mac_unit.v
// Single Multiply-Accumulate unit
// Takes 8-bit weight and 8-bit activation, multiplies, accumulates into 32-bit sum
module mac_unit (
    input  wire        clk,
    input  wire        rst,
    input  wire        enable,
    input  wire signed [7:0]  weight,
    input  wire signed [7:0]  activation,
    input  wire        clear_acc,
    output reg  signed [31:0] acc_out
);
    always @(posedge clk or posedge rst) begin
        if (rst) begin
            acc_out <= 32'sd0;
        end else if (clear_acc) begin
            acc_out <= 32'sd0;
        end else if (enable) begin
            acc_out <= acc_out + (weight * activation);
        end
    end
endmodule

laghu_npu/src/pe_array.v
// 4x4 array of MAC units - each PE has its own weight
module pe_array (
    input  wire clk,
    input  wire rst,
    input  wire enable,
    input  wire clear_acc,
    input  wire signed [7:0] w00, w01, w02, w03,
    input  wire signed [7:0] w10, w11, w12, w13,
    input  wire signed [7:0] w20, w21, w22, w23,
    input  wire signed [7:0] w30, w31, w32, w33,
    input  wire signed [7:0] act0, act1, act2, act3,
    output wire signed [31:0] r00, r01, r02, r03,
    output wire signed [31:0] r10, r11, r12, r13,
    output wire signed [31:0] r20, r21, r22, r23,
    output wire signed [31:0] r30, r31, r32, r33
);
    mac_unit u00 (clk, rst, enable, w00, act0, clear_acc, r00);
    mac_unit u01 (clk, rst, enable, w01, act1, clear_acc, r01);
    mac_unit u02 (clk, rst, enable, w02, act2, clear_acc, r02);
    mac_unit u03 (clk, rst, enable, w03, act3, clear_acc, r03);

    mac_unit u10 (clk, rst, enable, w10, act0, clear_acc, r10);
    mac_unit u11 (clk, rst, enable, w11, act1, clear_acc, r11);
    mac_unit u12 (clk, rst, enable, w12, act2, clear_acc, r12);
    mac_unit u13 (clk, rst, enable, w13, act3, clear_acc, r13);

    mac_unit u20 (clk, rst, enable, w20, act0, clear_acc, r20);
    mac_unit u21 (clk, rst, enable, w21, act1, clear_acc, r21);
    mac_unit u22 (clk, rst, enable, w22, act2, clear_acc, r22);
    mac_unit u23 (clk, rst, enable, w23, act3, clear_acc, r23);

    mac_unit u30 (clk, rst, enable, w30, act0, clear_acc, r30);
    mac_unit u31 (clk, rst, enable, w31, act1, clear_acc, r31);
    mac_unit u32 (clk, rst, enable, w32, act2, clear_acc, r32);
    mac_unit u33 (clk, rst, enable, w33, act3, clear_acc, r33);
endmodule

laghu_npu/src/laghu_npu_top.v
// Laghu-NPU Top Module
module laghu_npu_top (
    input  wire        clk,
    input  wire        rst,
    input  wire        start,
    output reg          done,
    input  wire        load_weights,
    input  wire [1:0]  weight_row_idx,
    input  wire signed [7:0] w_in0, w_in1, w_in2, w_in3,
    input  wire        load_activations,
    input  wire signed [7:0] a_in0, a_in1, a_in2, a_in3,
    output wire signed [31:0] out0, out1, out2, out3
);

    reg signed [7:0] w [0:3][0:3];
    reg signed [7:0] act0, act1, act2, act3;

    localparam IDLE    = 2'b00;
    localparam COMPUTE = 2'b01;
    localparam DONE_ST = 2'b10;

    reg [1:0] state;
    reg mac_enable;
    reg clear_acc;

    always @(posedge clk or posedge rst) begin
        if (rst) begin
            w[0][0] <= 0; w[0][1] <= 0; w[0][2] <= 0; w[0][3] <= 0;
            w[1][0] <= 0; w[1][1] <= 0; w[1][2] <= 0; w[1][3] <= 0;
            w[2][0] <= 0; w[2][1] <= 0; w[2][2] <= 0; w[2][3] <= 0;
            w[3][0] <= 0; w[3][1] <= 0; w[3][2] <= 0; w[3][3] <= 0;
        end else if (load_weights) begin
            w[weight_row_idx][0] <= w_in0;
            w[weight_row_idx][1] <= w_in1;
            w[weight_row_idx][2] <= w_in2;
            w[weight_row_idx][3] <= w_in3;
        end
    end

    always @(posedge clk or posedge rst) begin
        if (rst) begin
            act0 <= 0; act1 <= 0; act2 <= 0; act3 <= 0;
        end else if (load_activations) begin
            act0 <= a_in0;
            act1 <= a_in1;
            act2 <= a_in2;
            act3 <= a_in3;
        end
    end

    always @(posedge clk or posedge rst) begin
        if (rst) begin
            state      <= IDLE;
            mac_enable <= 1'b0;
            clear_acc  <= 1'b0;
            done       <= 1'b0;
        end else begin
            case (state)
                IDLE: begin
                    done <= 1'b0;
                    if (start) begin
                        clear_acc  <= 1'b1;
                        state      <= COMPUTE;
                    end
                end
                COMPUTE: begin
                    clear_acc  <= 1'b0;
                    mac_enable <= 1'b1;
                    state      <= DONE_ST;
                end
                DONE_ST: begin
                    mac_enable <= 1'b0;
                    done       <= 1'b1;
                    state      <= IDLE;
                end
                default: state <= IDLE;
            endcase
        end
    end

    wire signed [31:0] r00, r01, r02, r03;
    wire signed [31:0] r10, r11, r12, r13;
    wire signed [31:0] r20, r21, r22, r23;
    wire signed [31:0] r30, r31, r32, r33;

    pe_array u_pe_array (
        .clk(clk), .rst(rst), .enable(mac_enable), .clear_acc(clear_acc),
        .w00(w[0][0]), .w01(w[0][1]), .w02(w[0][2]), .w03(w[0][3]),
        .w10(w[1][0]), .w11(w[1][1]), .w12(w[1][2]), .w13(w[1][3]),
        .w20(w[2][0]), .w21(w[2][1]), .w22(w[2][2]), .w23(w[2][3]),
        .w30(w[3][0]), .w31(w[3][1]), .w32(w[3][2]), .w33(w[3][3]),
        .act0(act0), .act1(act1), .act2(act2), .act3(act3),
        .r00(r00), .r01(r01), .r02(r02), .r03(r03),
        .r10(r10), .r11(r11), .r12(r12), .r13(r13),
        .r20(r20), .r21(r21), .r22(r22), .r23(r23),
        .r30(r30), .r31(r31), .r32(r32), .r33(r33)
    );

    // Row-wise sum (dot product = sum of 4 products per row)
    wire signed [31:0] row0_sum, row1_sum, row2_sum, row3_sum;
    assign row0_sum = r00 + r01 + r02 + r03;
    assign row1_sum = r10 + r11 + r12 + r13;
    assign row2_sum = r20 + r21 + r22 + r23;
    assign row3_sum = r30 + r31 + r32 + r33;

    relu u_relu0 (.data_in(row0_sum), .data_out(out0));
    relu u_relu1 (.data_in(row1_sum), .data_out(out1));
    relu u_relu2 (.data_in(row2_sum), .data_out(out2));
    relu u_relu3 (.data_in(row3_sum), .data_out(out3));

endmodule

laghu_npu/tb/laghu_npu_tb.v
`timescale 1ns/1ps

module laghu_npu_tb;

    reg clk, rst;
    reg start, load_weights, load_activations;
    reg [1:0] weight_row_idx;
    reg signed [7:0] w_in0, w_in1, w_in2, w_in3;
    reg signed [7:0] a_in0, a_in1, a_in2, a_in3;
    wire done;
    wire signed [31:0] out0, out1, out2, out3;

    laghu_npu_top uut (
        .clk(clk), .rst(rst),
        .start(start), .done(done),
        .load_weights(load_weights), .weight_row_idx(weight_row_idx),
        .w_in0(w_in0), .w_in1(w_in1), .w_in2(w_in2), .w_in3(w_in3),
        .load_activations(load_activations),
        .a_in0(a_in0), .a_in1(a_in1), .a_in2(a_in2), .a_in3(a_in3),
        .out0(out0), .out1(out1), .out2(out2), .out3(out3)
    );

    // Clock generation: 10ns period
    always #5 clk = ~clk;

    initial begin
        $dumpfile("laghu_npu.vcd");
        $dumpvars(0, laghu_npu_tb);

        clk = 0;
        rst = 1;
        start = 0;
        load_weights = 0;
        load_activations = 0;
        weight_row_idx = 0;
        w_in0 = 0; w_in1 = 0; w_in2 = 0; w_in3 = 0;
        a_in0 = 0; a_in1 = 0; a_in2 = 0; a_in3 = 0;

        #20 rst = 0;

        // Load weight matrix (identity-like for easy verification)
        // Row 0: [2, 0, 0, 0]
        @(posedge clk);
        load_weights = 1; weight_row_idx = 0;
        w_in0 = 2; w_in1 = 0; w_in2 = 0; w_in3 = 0;
        @(posedge clk);
        // Row 1: [0, 3, 0, 0]
        weight_row_idx = 1;
        w_in0 = 0; w_in1 = 3; w_in2 = 0; w_in3 = 0;
        @(posedge clk);
        // Row 2: [0, 0, 4, 0]
        weight_row_idx = 2;
        w_in0 = 0; w_in1 = 0; w_in2 = 4; w_in3 = 0;
        @(posedge clk);
        // Row 3: [0, 0, 0, 5]
        weight_row_idx = 3;
        w_in0 = 0; w_in1 = 0; w_in2 = 0; w_in3 = 5;
        @(posedge clk);
        load_weights = 0;

        // Load activation vector [10, 10, 10, 10]
        load_activations = 1;
        a_in0 = 10; a_in1 = 10; a_in2 = 10; a_in3 = 10;
        @(posedge clk);
        load_activations = 0;

        // Start computation
        @(posedge clk);
        start = 1;
        @(posedge clk);
        start = 0;

        // Wait for done
        wait(done == 1);
        @(posedge clk);

        $display("========================================");
        $display("Laghu-NPU Test Results");
        $display("Expected: out0=20, out1=30, out2=40, out3=50");
        $display("Got:      out0=%0d, out1=%0d, out2=%0d, out3=%0d", out0, out1, out2, out3);
        $display("========================================");

        if (out0 == 20 && out1 == 30 && out2 == 40 && out3 == 50)
            $display("TEST PASSED!");
        else
            $display("TEST FAILED!");

        #20 $finish;
    end

endmodule

laghu_npu/src/laghu_npu.vcd
$date
	Sat Aug  1 03:05:28 2026
$end
$version
	Icarus Verilog
$end
$timescale
	1ps
$end
$scope module laghu_npu_tb $end
$var wire 32 ! out3 [31:0] $end
$var wire 32 " out2 [31:0] $end
$var wire 32 # out1 [31:0] $end
$var wire 32 $ out0 [31:0] $end
$var wire 1 % done $end
$var reg 8 & a_in0 [7:0] $end
$var reg 8 ' a_in1 [7:0] $end
$var reg 8 ( a_in2 [7:0] $end
$var reg 8 ) a_in3 [7:0] $end
$var reg 1 * clk $end
$var reg 1 + load_activations $end
$var reg 1 , load_weights $end
$var reg 1 - rst $end
$var reg 1 . start $end
$var reg 8 / w_in0 [7:0] $end
$var reg 8 0 w_in1 [7:0] $end
$var reg 8 1 w_in2 [7:0] $end
$var reg 8 2 w_in3 [7:0] $end
$var reg 2 3 weight_row_idx [1:0] $end
$scope module uut $end
$var wire 8 4 a_in0 [7:0] $end
$var wire 8 5 a_in1 [7:0] $end
$var wire 8 6 a_in2 [7:0] $end
$var wire 8 7 a_in3 [7:0] $end
$var wire 1 * clk $end
$var wire 1 + load_activations $end
$var wire 1 , load_weights $end
$var wire 1 - rst $end
$var wire 1 . start $end
$var wire 8 8 w_in0 [7:0] $end
$var wire 8 9 w_in1 [7:0] $end
$var wire 8 : w_in2 [7:0] $end
$var wire 8 ; w_in3 [7:0] $end
$var wire 2 < weight_row_idx [1:0] $end
$var wire 32 = row3_sum [31:0] $end
$var wire 32 > row2_sum [31:0] $end
$var wire 32 ? row1_sum [31:0] $end
$var wire 32 @ row0_sum [31:0] $end
$var wire 32 A r33 [31:0] $end
$var wire 32 B r32 [31:0] $end
$var wire 32 C r31 [31:0] $end
$var wire 32 D r30 [31:0] $end
$var wire 32 E r23 [31:0] $end
$var wire 32 F r22 [31:0] $end
$var wire 32 G r21 [31:0] $end
$var wire 32 H r20 [31:0] $end
$var wire 32 I r13 [31:0] $end
$var wire 32 J r12 [31:0] $end
$var wire 32 K r11 [31:0] $end
$var wire 32 L r10 [31:0] $end
$var wire 32 M r03 [31:0] $end
$var wire 32 N r02 [31:0] $end
$var wire 32 O r01 [31:0] $end
$var wire 32 P r00 [31:0] $end
$var wire 32 Q out3 [31:0] $end
$var wire 32 R out2 [31:0] $end
$var wire 32 S out1 [31:0] $end
$var wire 32 T out0 [31:0] $end
$var parameter 2 U COMPUTE $end
$var parameter 2 V DONE_ST $end
$var parameter 2 W IDLE $end
$var reg 8 X act0 [7:0] $end
$var reg 8 Y act1 [7:0] $end
$var reg 8 Z act2 [7:0] $end
$var reg 8 [ act3 [7:0] $end
$var reg 1 \ clear_acc $end
$var reg 1 % done $end
$var reg 1 ] mac_enable $end
$var reg 2 ^ state [1:0] $end
$scope module u_pe_array $end
$var wire 8 _ act0 [7:0] $end
$var wire 8 ` act1 [7:0] $end
$var wire 8 a act2 [7:0] $end
$var wire 8 b act3 [7:0] $end
$var wire 1 \ clear_acc $end
$var wire 1 * clk $end
$var wire 1 ] enable $end
$var wire 1 - rst $end
$var wire 8 c w00 [7:0] $end
$var wire 8 d w01 [7:0] $end
$var wire 8 e w02 [7:0] $end
$var wire 8 f w03 [7:0] $end
$var wire 8 g w10 [7:0] $end
$var wire 8 h w11 [7:0] $end
$var wire 8 i w12 [7:0] $end
$var wire 8 j w13 [7:0] $end
$var wire 8 k w20 [7:0] $end
$var wire 8 l w21 [7:0] $end
$var wire 8 m w22 [7:0] $end
$var wire 8 n w23 [7:0] $end
$var wire 8 o w30 [7:0] $end
$var wire 8 p w31 [7:0] $end
$var wire 8 q w32 [7:0] $end
$var wire 8 r w33 [7:0] $end
$var wire 32 s r33 [31:0] $end
$var wire 32 t r32 [31:0] $end
$var wire 32 u r31 [31:0] $end
$var wire 32 v r30 [31:0] $end
$var wire 32 w r23 [31:0] $end
$var wire 32 x r22 [31:0] $end
$var wire 32 y r21 [31:0] $end
$var wire 32 z r20 [31:0] $end
$var wire 32 { r13 [31:0] $end
$var wire 32 | r12 [31:0] $end
$var wire 32 } r11 [31:0] $end
$var wire 32 ~ r10 [31:0] $end
$var wire 32 !" r03 [31:0] $end
$var wire 32 "" r02 [31:0] $end
$var wire 32 #" r01 [31:0] $end
$var wire 32 $" r00 [31:0] $end
$scope module u00 $end
$var wire 8 %" activation [7:0] $end
$var wire 1 \ clear_acc $end
$var wire 1 * clk $end
$var wire 1 ] enable $end
$var wire 1 - rst $end
$var wire 8 &" weight [7:0] $end
$var reg 32 '" acc_out [31:0] $end
$upscope $end
$scope module u01 $end
$var wire 8 (" activation [7:0] $end
$var wire 1 \ clear_acc $end
$var wire 1 * clk $end
$var wire 1 ] enable $end
$var wire 1 - rst $end
$var wire 8 )" weight [7:0] $end
$var reg 32 *" acc_out [31:0] $end
$upscope $end
$scope module u02 $end
$var wire 8 +" activation [7:0] $end
$var wire 1 \ clear_acc $end
$var wire 1 * clk $end
$var wire 1 ] enable $end
$var wire 1 - rst $end
$var wire 8 ," weight [7:0] $end
$var reg 32 -" acc_out [31:0] $end
$upscope $end
$scope module u03 $end
$var wire 8 ." activation [7:0] $end
$var wire 1 \ clear_acc $end
$var wire 1 * clk $end
$var wire 1 ] enable $end
$var wire 1 - rst $end
$var wire 8 /" weight [7:0] $end
$var reg 32 0" acc_out [31:0] $end
$upscope $end
$scope module u10 $end
$var wire 8 1" activation [7:0] $end
$var wire 1 \ clear_acc $end
$var wire 1 * clk $end
$var wire 1 ] enable $end
$var wire 1 - rst $end
$var wire 8 2" weight [7:0] $end
$var reg 32 3" acc_out [31:0] $end
$upscope $end
$scope module u11 $end
$var wire 8 4" activation [7:0] $end
$var wire 1 \ clear_acc $end
$var wire 1 * clk $end
$var wire 1 ] enable $end
$var wire 1 - rst $end
$var wire 8 5" weight [7:0] $end
$var reg 32 6" acc_out [31:0] $end
$upscope $end
$scope module u12 $end
$var wire 8 7" activation [7:0] $end
$var wire 1 \ clear_acc $end
$var wire 1 * clk $end
$var wire 1 ] enable $end
$var wire 1 - rst $end
$var wire 8 8" weight [7:0] $end
$var reg 32 9" acc_out [31:0] $end
$upscope $end
$scope module u13 $end
$var wire 8 :" activation [7:0] $end
$var wire 1 \ clear_acc $end
$var wire 1 * clk $end
$var wire 1 ] enable $end
$var wire 1 - rst $end
$var wire 8 ;" weight [7:0] $end
$var reg 32 <" acc_out [31:0] $end
$upscope $end
$scope module u20 $end
$var wire 8 =" activation [7:0] $end
$var wire 1 \ clear_acc $end
$var wire 1 * clk $end
$var wire 1 ] enable $end
$var wire 1 - rst $end
$var wire 8 >" weight [7:0] $end
$var reg 32 ?" acc_out [31:0] $end
$upscope $end
$scope module u21 $end
$var wire 8 @" activation [7:0] $end
$var wire 1 \ clear_acc $end
$var wire 1 * clk $end
$var wire 1 ] enable $end
$var wire 1 - rst $end
$var wire 8 A" weight [7:0] $end
$var reg 32 B" acc_out [31:0] $end
$upscope $end
$scope module u22 $end
$var wire 8 C" activation [7:0] $end
$var wire 1 \ clear_acc $end
$var wire 1 * clk $end
$var wire 1 ] enable $end
$var wire 1 - rst $end
$var wire 8 D" weight [7:0] $end
$var reg 32 E" acc_out [31:0] $end
$upscope $end
$scope module u23 $end
$var wire 8 F" activation [7:0] $end
$var wire 1 \ clear_acc $end
$var wire 1 * clk $end
$var wire 1 ] enable $end
$var wire 1 - rst $end
$var wire 8 G" weight [7:0] $end
$var reg 32 H" acc_out [31:0] $end
$upscope $end
$scope module u30 $end
$var wire 8 I" activation [7:0] $end
$var wire 1 \ clear_acc $end
$var wire 1 * clk $end
$var wire 1 ] enable $end
$var wire 1 - rst $end
$var wire 8 J" weight [7:0] $end
$var reg 32 K" acc_out [31:0] $end
$upscope $end
$scope module u31 $end
$var wire 8 L" activation [7:0] $end
$var wire 1 \ clear_acc $end
$var wire 1 * clk $end
$var wire 1 ] enable $end
$var wire 1 - rst $end
$var wire 8 M" weight [7:0] $end
$var reg 32 N" acc_out [31:0] $end
$upscope $end
$scope module u32 $end
$var wire 8 O" activation [7:0] $end
$var wire 1 \ clear_acc $end
$var wire 1 * clk $end
$var wire 1 ] enable $end
$var wire 1 - rst $end
$var wire 8 P" weight [7:0] $end
$var reg 32 Q" acc_out [31:0] $end
$upscope $end
$scope module u33 $end
$var wire 8 R" activation [7:0] $end
$var wire 1 \ clear_acc $end
$var wire 1 * clk $end
$var wire 1 ] enable $end
$var wire 1 - rst $end
$var wire 8 S" weight [7:0] $end
$var reg 32 T" acc_out [31:0] $end
$upscope $end
$upscope $end
$scope module u_relu0 $end
$var wire 32 U" data_in [31:0] $end
$var wire 32 V" data_out [31:0] $end
$upscope $end
$scope module u_relu1 $end
$var wire 32 W" data_in [31:0] $end
$var wire 32 X" data_out [31:0] $end
$upscope $end
$scope module u_relu2 $end
$var wire 32 Y" data_in [31:0] $end
$var wire 32 Z" data_out [31:0] $end
$upscope $end
$scope module u_relu3 $end
$var wire 32 [" data_in [31:0] $end
$var wire 32 \" data_out [31:0] $end
$upscope $end
$upscope $end
$upscope $end
$enddefinitions $end
$comment Show the parameter values. $end
$dumpall
b0 W
b10 V
b1 U
$end
#0
$dumpvars
b0 \"
b0 ["
b0 Z"
b0 Y"
b0 X"
b0 W"
b0 V"
b0 U"
b0 T"
b0 S"
b0 R"
b0 Q"
b0 P"
b0 O"
b0 N"
b0 M"
b0 L"
b0 K"
b0 J"
b0 I"
b0 H"
b0 G"
b0 F"
b0 E"
b0 D"
b0 C"
b0 B"
b0 A"
b0 @"
b0 ?"
b0 >"
b0 ="
b0 <"
b0 ;"
b0 :"
b0 9"
b0 8"
b0 7"
b0 6"
b0 5"
b0 4"
b0 3"
b0 2"
b0 1"
b0 0"
b0 /"
b0 ."
b0 -"
b0 ,"
b0 +"
b0 *"
b0 )"
b0 ("
b0 '"
b0 &"
b0 %"
b0 $"
b0 #"
b0 ""
b0 !"
b0 ~
b0 }
b0 |
b0 {
b0 z
b0 y
b0 x
b0 w
b0 v
b0 u
b0 t
b0 s
b0 r
b0 q
b0 p
b0 o
b0 n
b0 m
b0 l
b0 k
b0 j
b0 i
b0 h
b0 g
b0 f
b0 e
b0 d
b0 c
b0 b
b0 a
b0 `
b0 _
b0 ^
0]
0\
b0 [
b0 Z
b0 Y
b0 X
b0 T
b0 S
b0 R
b0 Q
b0 P
b0 O
b0 N
b0 M
b0 L
b0 K
b0 J
b0 I
b0 H
b0 G
b0 F
b0 E
b0 D
b0 C
b0 B
b0 A
b0 @
b0 ?
b0 >
b0 =
b0 <
b0 ;
b0 :
b0 9
b0 8
b0 7
b0 6
b0 5
b0 4
b0 3
b0 2
b0 1
b0 0
b0 /
0.
1-
0,
0+
0*
b0 )
b0 (
b0 '
b0 &
0%
b0 $
b0 #
b0 "
b0 !
$end
#5000
1*
#10000
0*
#15000
1*
#20000
0*
0-
#25000
b10 c
b10 &"
b10 /
b10 8
1,
1*
#30000
0*
#35000
b11 h
b11 5"
b11 0
b11 9
b0 /
b0 8
b1 3
b1 <
1*
#40000
0*
#45000
b100 m
b100 D"
b100 1
b100 :
b0 0
b0 9
b10 3
b10 <
1*
#50000
0*
#55000
b101 r
b101 S"
b101 2
b101 ;
b0 1
b0 :
b11 3
b11 <
1*
#60000
0*
#65000
b1010 [
b1010 b
b1010 ."
b1010 :"
b1010 F"
b1010 R"
b1010 Z
b1010 a
b1010 +"
b1010 7"
b1010 C"
b1010 O"
b1010 Y
b1010 `
b1010 ("
b1010 4"
b1010 @"
b1010 L"
b1010 X
b1010 _
b1010 %"
b1010 1"
b1010 ="
b1010 I"
b1010 )
b1010 7
b1010 (
b1010 6
b1010 '
b1010 5
b1010 &
b1010 4
1+
0,
1*
#70000
0*
#75000
0+
1*
#80000
0*
#85000
b1 ^
1\
1.
1*
#90000
0*
#95000
b10 ^
1]
0\
0.
1*
#100000
0*
#105000
b110010 !
b110010 Q
b110010 \"
b101000 "
b101000 R
b101000 Z"
b11110 #
b11110 S
b11110 X"
b10100 $
b10100 T
b10100 V"
b0 ^
1%
0]
b110010 =
b110010 ["
b110010 A
b110010 s
b110010 T"
b101000 >
b101000 Y"
b101000 F
b101000 x
b101000 E"
b11110 ?
b11110 W"
b11110 K
b11110 }
b11110 6"
b10100 @
b10100 U"
b10100 P
b10100 $"
b10100 '"
1*
#110000
0*
#115000
0%
1*
