day3/alu.v
module alu(
    input  wire [3:0] a,
    input  wire [3:0] b,
    input  wire [2:0] op,
    output reg  [4:0] result,
    output reg        zero
);

    // Operations
    parameter ADD = 3'b000;
    parameter SUB = 3'b001;
    parameter AND = 3'b010;
    parameter OR  = 3'b011;
    parameter XOR = 3'b100;
    parameter NOT = 3'b101;
    parameter SHL = 3'b110;
    parameter SHR = 3'b111;

    always @(*) begin
        case (op)
            ADD: result = a + b;
            SUB: result = a - b;
            AND: result = a & b;
            OR:  result = a | b;
            XOR: result = a ^ b;
            NOT: result = ~a;
            SHL: result = a << 1;
            SHR: result = a >> 1;
            default: result = 0;
        endcase
        zero = (result == 0) ? 1 : 0;
    end

endmodule

day7/reg_file.v
module reg_file(
    input  wire        clk,
    input  wire        rst,
    input  wire        wr_en,
    input  wire [2:0]  wr_addr,
    input  wire [7:0]  wr_data,
    input  wire [2:0]  rd_addr1,
    input  wire [2:0]  rd_addr2,
    output wire [7:0]  rd_data1,
    output wire [7:0]  rd_data2
);
    // 8 registers, har ek 8-bit
    reg [7:0] registers [0:7];
    integer i;

    // Write operation
    always @(posedge clk or posedge rst) begin
        if (rst) begin
            for (i=0; i<8; i=i+1)
                registers[i] <= 8'b0;
        end
        else if (wr_en) begin
            registers[wr_addr] <= wr_data;
        end
    end

    // Read operation
    assign rd_data1 = registers[rd_addr1];
    assign rd_data2 = registers[rd_addr2];

endmodule

day5/cpu.v
module cpu(
    input  wire        clk,
    input  wire        rst,
    input  wire [7:0]  instruction,
    output wire [7:0]  result
);

    // Instruction decode
    wire [1:0] opcode  = instruction[7:6];
    wire [2:0] reg_a   = instruction[5:3];
    wire [2:0] reg_b   = instruction[2:0];

    // Register file signals
    wire [7:0] data_a, data_b;
    reg  [7:0] wr_data;
    reg        wr_en;
    reg  [2:0] wr_addr;

    // ALU signals
    wire [4:0] alu_out;
    reg  [2:0] alu_op;

    // Register File
    reg_file RF (
        .clk(clk), .rst(rst),
        .wr_en(wr_en),
        .wr_addr(wr_addr),
        .wr_data(wr_data),
        .rd_addr1(reg_a),
        .rd_addr2(reg_b),
        .rd_data1(data_a),
        .rd_data2(data_b)
    );

    // ALU — sirf 4-bit use karo
    alu ALU (
        .a(data_a[3:0]),
        .b(data_b[3:0]),
        .op(alu_op),
        .result(alu_out),
        .zero()
    );

    // Instruction decode logic
    always @(*) begin
        case (opcode)
            2'b00: alu_op = 3'b000; // ADD
            2'b01: alu_op = 3'b001; // SUB
            2'b10: alu_op = 3'b010; // AND
            2'b11: alu_op = 3'b011; // OR
        endcase
        wr_en   = 1;
        wr_addr = reg_a;
        wr_data = {3'b0, alu_out};
    end

    assign result = {3'b0, alu_out};

endmodule

day5/cpu_tb.v
module cpu_tb;

    reg        clk, rst;
    reg  [7:0] instruction;
    wire [7:0] result;

    cpu uut (
        .clk(clk),
        .rst(rst),
        .instruction(instruction),
        .result(result)
    );

    initial clk = 0;
    always #5 clk = ~clk;

    initial begin
        $dumpfile("cpu.vcd");
        $dumpvars(0, cpu_tb);

        // Reset
        rst=1; instruction=8'b0; #20;
        rst=0; #10;

        // R0 mein 5 store karo
        // Pehle manually register load karenge
        // instruction = opcode(2) + reg_a(3) + reg_b(3)

        // ADD R0 + R1 — opcode=00, a=000, b=001
        instruction = 8'b00_000_001; #20;
        $display("ADD R0+R1 = %0d", result);

        // AND R2 + R3 — opcode=10, a=010, b=011
        instruction = 8'b10_010_011; #20;
        $display("AND R2&R3 = %0d", result);

        // OR R4 + R5 — opcode=11, a=100, b=101
        instruction = 8'b11_100_101; #20;
        $display("OR  R4|R5 = %0d", result);

        // SUB R6 - R7 — opcode=01, a=110, b=111
        instruction = 8'b01_110_111; #20;
        $display("SUB R6-R7 = %0d", result);

        $display("Day 5 Complete! CPU working!");
        $finish;
    end

endmodule

day5/cpu.vcd
$date
	Mon Jul 27 18:46:01 2026
$end
$version
	Icarus Verilog
$end
$timescale
	1s
$end
$scope module cpu_tb $end
$var wire 8 ! result [7:0] $end
$var reg 1 " clk $end
$var reg 8 # instruction [7:0] $end
$var reg 1 $ rst $end
$scope module uut $end
$var wire 1 " clk $end
$var wire 8 % instruction [7:0] $end
$var wire 1 $ rst $end
$var wire 8 & result [7:0] $end
$var wire 3 ' reg_b [2:0] $end
$var wire 3 ( reg_a [2:0] $end
$var wire 2 ) opcode [1:0] $end
$var wire 8 * data_b [7:0] $end
$var wire 8 + data_a [7:0] $end
$var wire 5 , alu_out [4:0] $end
$var reg 3 - alu_op [2:0] $end
$var reg 3 . wr_addr [2:0] $end
$var reg 8 / wr_data [7:0] $end
$var reg 1 0 wr_en $end
$scope module ALU $end
$var wire 4 1 a [3:0] $end
$var wire 4 2 b [3:0] $end
$var wire 3 3 op [2:0] $end
$var parameter 3 4 ADD $end
$var parameter 3 5 AND $end
$var parameter 3 6 NOT $end
$var parameter 3 7 OR $end
$var parameter 3 8 SHL $end
$var parameter 3 9 SHR $end
$var parameter 3 : SUB $end
$var parameter 3 ; XOR $end
$var reg 5 < result [4:0] $end
$var reg 1 = zero $end
$upscope $end
$scope module RF $end
$var wire 1 " clk $end
$var wire 3 > rd_addr1 [2:0] $end
$var wire 3 ? rd_addr2 [2:0] $end
$var wire 8 @ rd_data1 [7:0] $end
$var wire 8 A rd_data2 [7:0] $end
$var wire 1 $ rst $end
$var wire 3 B wr_addr [2:0] $end
$var wire 8 C wr_data [7:0] $end
$var wire 1 0 wr_en $end
$var integer 32 D i [31:0] $end
$upscope $end
$upscope $end
$upscope $end
$enddefinitions $end
$comment Show the parameter values. $end
$dumpall
b100 ;
b1 :
b111 9
b110 8
b11 7
b101 6
b10 5
b0 4
$end
#0
$dumpvars
b1000 D
b0 C
b0 B
b0 A
b0 @
b0 ?
b0 >
1=
b0 <
b0 3
b0 2
b0 1
10
b0 /
b0 .
b0 -
b0 ,
b0 +
b0 *
b0 )
b0 (
b0 '
b0 &
b0 %
1$
b0 #
0"
b0 !
$end
#5
b1000 D
1"
#10
0"
#15
b1000 D
1"
#20
0"
0$
#25
1"
#30
b1 '
b1 ?
0"
b1 #
b1 %
#35
1"
#40
0"
#45
1"
#50
b10 .
b10 B
b10 -
b10 3
b10 )
b10 (
b10 >
b11 '
b11 ?
0"
b10010011 #
b10010011 %
#55
1"
#60
0"
#65
1"
#70
b100 .
b100 B
b11 -
b11 3
b11 )
b100 (
b100 >
b101 '
b101 ?
0"
b11100101 #
b11100101 %
#75
1"
#80
0"
#85
1"
#90
b110 .
b110 B
b1 -
b1 3
b1 )
b110 (
b110 >
b111 '
b111 ?
0"
b1110111 #
b1110111 %
