day3/alu.v
module alu(
    input  wire [3:0] a,
    input  wire [3:0] b,
    input  wire [2:0] op,
    output reg  [4:0] result,
    output reg        zero
);

    // Operations
    parameter ADD = 3'b000;
    parameter SUB = 3'b001;
    parameter AND = 3'b010;
    parameter OR  = 3'b011;
    parameter XOR = 3'b100;
    parameter NOT = 3'b101;
    parameter SHL = 3'b110;
    parameter SHR = 3'b111;

    always @(*) begin
        case (op)
            ADD: result = a + b;
            SUB: result = a - b;
            AND: result = a & b;
            OR:  result = a | b;
            XOR: result = a ^ b;
            NOT: result = ~a;
            SHL: result = a << 1;
            SHR: result = a >> 1;
            default: result = 0;
        endcase
        zero = (result == 0) ? 1 : 0;
    end

endmodule

day7/reg_file.v
module reg_file(
    input  wire        clk,
    input  wire        rst,
    input  wire        wr_en,
    input  wire [2:0]  wr_addr,
    input  wire [7:0]  wr_data,
    input  wire [2:0]  rd_addr1,
    input  wire [2:0]  rd_addr2,
    output wire [7:0]  rd_data1,
    output wire [7:0]  rd_data2
);
    // 8 registers, har ek 8-bit
    reg [7:0] registers [0:7];
    integer i;

    // Write operation
    always @(posedge clk or posedge rst) begin
        if (rst) begin
            for (i=0; i<8; i=i+1)
                registers[i] <= 8'b0;
        end
        else if (wr_en) begin
            registers[wr_addr] <= wr_data;
        end
    end

    // Read operation
    assign rd_data1 = registers[rd_addr1];
    assign rd_data2 = registers[rd_addr2];

endmodule

day8/pipeline.v
module pipeline(
    input  wire        clk,
    input  wire        rst,
    output reg  [7:0]  result,
    output reg  [2:0]  pc_out
);

    // ─── STAGE 1: FETCH ───
    reg [2:0] if_pc;
    reg [7:0] if_instruction;

    // Instruction Memory
    reg [7:0] imem [0:7];
    initial begin
        imem[0] = 8'b00_000_001; // ADD R0+R1
        imem[1] = 8'b00_010_011; // ADD R2+R3
        imem[2] = 8'b01_000_010; // SUB R0-R2
        imem[3] = 8'b10_001_011; // AND R1&R3
        imem[4] = 8'b11_000_001; // OR  R0|R1
        imem[5] = 8'b00_100_101; // ADD R4+R5
        imem[6] = 8'b01_110_111; // SUB R6-R7
        imem[7] = 8'b10_000_001; // AND R0&R1
    end

    // PC counter
    always @(posedge clk or posedge rst) begin
        if (rst) if_pc <= 0;
        else if (if_pc == 7) if_pc <= 0;
        else if_pc <= if_pc + 1;
    end

    always @(*) if_instruction = imem[if_pc];

    // ─── IF/ID PIPELINE REGISTER ───
    reg [7:0] id_instruction;
    reg [2:0] id_pc;

    always @(posedge clk or posedge rst) begin
        if (rst) begin
            id_instruction <= 0;
            id_pc <= 0;
        end else begin
            id_instruction <= if_instruction;
            id_pc <= if_pc;
        end
    end

    // ─── STAGE 2: DECODE ───
    wire [1:0] id_opcode = id_instruction[7:6];
    wire [2:0] id_reg_a  = id_instruction[5:3];
    wire [2:0] id_reg_b  = id_instruction[2:0];

    wire [7:0] id_data_a, id_data_b;

    reg_file RF (
        .clk(clk), .rst(rst),
        .wr_en(1'b1),
        .wr_addr(id_reg_a),
        .wr_data(result),
        .rd_addr1(id_reg_a),
        .rd_addr2(id_reg_b),
        .rd_data1(id_data_a),
        .rd_data2(id_data_b)
    );

    // ─── ID/EX PIPELINE REGISTER ───
    reg [1:0] ex_opcode;
    reg [7:0] ex_data_a, ex_data_b;
    reg [2:0] ex_pc;

    always @(posedge clk or posedge rst) begin
        if (rst) begin
            ex_opcode <= 0;
            ex_data_a <= 0;
            ex_data_b <= 0;
            ex_pc     <= 0;
        end else begin
            ex_opcode <= id_opcode;
            ex_data_a <= id_data_a;
            ex_data_b <= id_data_b;
            ex_pc     <= id_pc;
        end
    end

    // ─── STAGE 3: EXECUTE ───
    wire [4:0] alu_out;
    reg  [2:0] alu_op;

    always @(*) begin
        case (ex_opcode)
            2'b00: alu_op = 3'b000; // ADD
            2'b01: alu_op = 3'b001; // SUB
            2'b10: alu_op = 3'b010; // AND
            2'b11: alu_op = 3'b011; // OR
        endcase
    end

    alu ALU (
        .a(ex_data_a[3:0]),
        .b(ex_data_b[3:0]),
        .op(alu_op),
        .result(alu_out),
        .zero()
    );

    // ─── WRITEBACK ───
    always @(posedge clk or posedge rst) begin
        if (rst) begin
            result <= 0;
            pc_out <= 0;
        end else begin
            result <= {3'b0, alu_out};
            pc_out <= ex_pc;
        end
    end

endmodule

day8/pipeline_tb.v
module pipeline_tb;

    reg        clk, rst;
    wire [7:0] result;
    wire [2:0] pc_out;

    pipeline uut (
        .clk(clk), .rst(rst),
        .result(result),
        .pc_out(pc_out)
    );

    initial clk = 0;
    always #5 clk = ~clk;

    initial begin
        $dumpfile("pipeline.vcd");
        $dumpvars(0, pipeline_tb);

        rst=1; #30;
        rst=0;

        $display("================================");
        $display("  PIPELINED CPU — 3 STAGE      ");
        $display("  FETCH | DECODE | EXECUTE      ");
        $display("================================");

        repeat(20) begin
            #10;
            $display("PC=%0d | Result=%0d", pc_out, result);
        end

        $display("================================");
        $display("Day 8 Complete! Pipeline working!");
        $display("3-stage: Fetch+Decode+Execute!");
        $display("================================");
        $finish;
    end

endmodule

day8/pipeline.vcd
$date
	Mon Jul 27 18:51:16 2026
$end
$version
	Icarus Verilog
$end
$timescale
	1s
$end
$scope module pipeline_tb $end
$var wire 8 ! result [7:0] $end
$var wire 3 " pc_out [2:0] $end
$var reg 1 # clk $end
$var reg 1 $ rst $end
$scope module uut $end
$var wire 1 # clk $end
$var wire 1 $ rst $end
$var wire 3 % id_reg_b [2:0] $end
$var wire 3 & id_reg_a [2:0] $end
$var wire 2 ' id_opcode [1:0] $end
$var wire 8 ( id_data_b [7:0] $end
$var wire 8 ) id_data_a [7:0] $end
$var wire 5 * alu_out [4:0] $end
$var reg 3 + alu_op [2:0] $end
$var reg 8 , ex_data_a [7:0] $end
$var reg 8 - ex_data_b [7:0] $end
$var reg 2 . ex_opcode [1:0] $end
$var reg 3 / ex_pc [2:0] $end
$var reg 8 0 id_instruction [7:0] $end
$var reg 3 1 id_pc [2:0] $end
$var reg 8 2 if_instruction [7:0] $end
$var reg 3 3 if_pc [2:0] $end
$var reg 3 4 pc_out [2:0] $end
$var reg 8 5 result [7:0] $end
$scope module ALU $end
$var wire 4 6 a [3:0] $end
$var wire 4 7 b [3:0] $end
$var wire 3 8 op [2:0] $end
$var parameter 3 9 ADD $end
$var parameter 3 : AND $end
$var parameter 3 ; NOT $end
$var parameter 3 < OR $end
$var parameter 3 = SHL $end
$var parameter 3 > SHR $end
$var parameter 3 ? SUB $end
$var parameter 3 @ XOR $end
$var reg 5 A result [4:0] $end
$var reg 1 B zero $end
$upscope $end
$scope module RF $end
$var wire 1 # clk $end
$var wire 3 C rd_addr1 [2:0] $end
$var wire 3 D rd_addr2 [2:0] $end
$var wire 8 E rd_data1 [7:0] $end
$var wire 8 F rd_data2 [7:0] $end
$var wire 1 $ rst $end
$var wire 3 G wr_addr [2:0] $end
$var wire 8 H wr_data [7:0] $end
$var wire 1 I wr_en $end
$var integer 32 J i [31:0] $end
$upscope $end
$upscope $end
$upscope $end
$enddefinitions $end
$comment Show the parameter values. $end
$dumpall
b100 @
b1 ?
b111 >
b110 =
b11 <
b101 ;
b10 :
b0 9
$end
#0
$dumpvars
b1000 J
1I
b0 H
b0 G
b0 F
b0 E
b0 D
b0 C
1B
b0 A
b0 8
b0 7
b0 6
b0 5
b0 4
b0 3
b1 2
b0 1
b0 0
b0 /
b0 .
b0 -
b0 ,
b0 +
b0 *
b0 )
b0 (
b0 '
b0 &
b0 %
1$
0#
b0 "
b0 !
$end
#5
b1000 J
1#
#10
0#
#15
b1000 J
1#
#20
0#
#25
b1000 J
1#
#30
0#
0$
#35
b10011 2
b1 %
b1 D
b1 3
b1 0
1#
#40
0#
#45
b10 &
b10 C
b10 G
b11 %
b11 D
b1000010 2
b1 1
b10011 0
b10 3
1#
#50
0#
#55
b10001011 2
b1 '
b0 &
b0 C
b0 G
b10 %
b10 D
b11 3
b10 1
b1000010 0
b1 /
1#
#60
0#
#65
b1 +
b1 8
b10 '
b1 &
b1 C
b1 G
b11 %
b11 D
b11000001 2
b1 "
b1 4
b10 /
b1 .
b11 1
b10001011 0
b100 3
1#
#70
0#
#75
b100101 2
b11 '
b0 &
b0 C
b0 G
b1 %
b1 D
b10 +
b10 8
b101 3
b100 1
b11000001 0
b11 /
b10 .
b10 "
b10 4
1#
#80
0#
#85
b11 +
b11 8
b0 '
b100 &
b100 C
b100 G
b101 %
b101 D
b1110111 2
b11 "
b11 4
b100 /
b11 .
b101 1
b100101 0
b110 3
1#
#90
0#
#95
b10000001 2
b1 '
b110 &
b110 C
b110 G
b111 %
b111 D
b0 +
b0 8
b111 3
b110 1
b1110111 0
b101 /
b0 .
b100 "
b100 4
1#
#100
0#
#105
b1 +
b1 8
b10 '
b0 &
b0 C
b0 G
b1 %
b1 D
b1 2
b101 "
b101 4
b110 /
b1 .
b111 1
b10000001 0
b0 3
1#
#110
0#
#115
b10011 2
b0 '
b10 +
b10 8
b1 3
b0 1
b1 0
b111 /
b10 .
b110 "
b110 4
1#
#120
0#
#125
b0 +
b0 8
b10 &
b10 C
b10 G
b11 %
b11 D
b1000010 2
b111 "
b111 4
b0 /
b0 .
b1 1
b10011 0
b10 3
1#
#130
0#
#135
b10001011 2
b1 '
b0 &
b0 C
b0 G
b10 %
b10 D
b11 3
b10 1
b1000010 0
b1 /
b0 "
b0 4
1#
#140
0#
#145
b1 +
b1 8
b10 '
b1 &
b1 C
b1 G
b11 %
b11 D
b11000001 2
b1 "
b1 4
b10 /
b1 .
b11 1
b10001011 0
b100 3
1#
#150
0#
#155
b100101 2
b11 '
b0 &
b0 C
b0 G
b1 %
b1 D
b10 +
b10 8
b101 3
b100 1
b11000001 0
b11 /
b10 .
b10 "
b10 4
1#
#160
0#
#165
b11 +
b11 8
b0 '
b100 &
b100 C
b100 G
b101 %
b101 D
b1110111 2
b11 "
b11 4
b100 /
b11 .
b101 1
b100101 0
b110 3
1#
#170
0#
#175
b10000001 2
b1 '
b110 &
b110 C
b110 G
b111 %
b111 D
b0 +
b0 8
b111 3
b110 1
b1110111 0
b101 /
b0 .
b100 "
b100 4
1#
#180
0#
#185
b1 +
b1 8
b10 '
b0 &
b0 C
b0 G
b1 %
b1 D
b1 2
b101 "
b101 4
b110 /
b1 .
b111 1
b10000001 0
b0 3
1#
#190
0#
#195
b10011 2
b0 '
b10 +
b10 8
b1 3
b0 1
b1 0
b111 /
b10 .
b110 "
b110 4
1#
#200
0#
#205
b0 +
b0 8
b10 &
b10 C
b10 G
b11 %
b11 D
b1000010 2
b111 "
b111 4
b0 /
b0 .
b1 1
b10011 0
b10 3
1#
#210
0#
#215
b10001011 2
b1 '
b0 &
b0 C
b0 G
b10 %
b10 D
b11 3
b10 1
b1000010 0
b1 /
b0 "
b0 4
1#
#220
0#
#225
b1 +
b1 8
b10 '
b1 &
b1 C
b1 G
b11 %
b11 D
b11000001 2
b1 "
b1 4
b10 /
b1 .
b11 1
b10001011 0
b100 3
1#
