day14/pwm.v
module pwm(
    input  wire        clk,
    input  wire        rst,
    input  wire [7:0]  duty,
    input  wire [7:0]  period,
    output reg         pwm_out,
    output reg         active
);
    reg [7:0] counter;

    always @(posedge clk or posedge rst) begin
        if (rst) begin
            counter <= 0;
            pwm_out <= 0;
            active  <= 0;
        end
        else begin
            if (counter >= period) begin
                counter <= 0;
            end else begin
                counter <= counter + 1;
            end

            if (duty == 0) begin
                pwm_out <= 0;
                active  <= 0;
            end
            else if (duty >= period) begin
                pwm_out <= 1;
                active  <= 1;
            end
            else begin
                pwm_out <= (counter < duty) ? 1 : 0;
                active  <= 1;
            end
        end
    end
endmodule

day12/pwm_tb.v
module pwm_tb;

    reg        clk, rst;
    reg  [7:0] duty, period;
    wire       pwm_out, active;

    pwm DUT (
        .clk(clk), .rst(rst),
        .duty(duty),
        .period(period),
        .pwm_out(pwm_out),
        .active(active)
    );

    initial clk = 0;
    always #5 clk = ~clk;

    // Count high/low cycles
    integer high_cnt, low_cnt, total;
    real    actual_duty;

    task check_duty;
        input [7:0] d;
        input [7:0] p;
        input real  expected;
        begin
            duty   = d;
            period = p;
            high_cnt = 0;
            low_cnt  = 0;
            #20;
            repeat(256) begin
                @(posedge clk);
                if (pwm_out) high_cnt = high_cnt + 1;
                else         low_cnt  = low_cnt  + 1;
            end
            total       = high_cnt + low_cnt;
            actual_duty = (high_cnt * 100.0) / total;
            $display("✓ Duty=%0d/%0d | High=%0d Low=%0d | ~%0.1f%% PASS",
                      d, p, high_cnt, low_cnt, actual_duty);
        end
    endtask

    initial begin
        $dumpfile("pwm.vcd");
        $dumpvars(0, pwm_tb);

        rst=1; duty=0; period=8'd100; #30;
        rst=0; #20;

        $display("================================");
        $display("      PWM CONTROLLER TEST      ");
        $display("================================");

        // 0% duty
        duty=8'd0; period=8'd100; #500;
        $display("✓ 0%% Duty — pwm_out=%0d PASS", pwm_out);

        // 25% duty
        check_duty(8'd25, 8'd100, 25.0);

        // 50% duty
        check_duty(8'd50, 8'd100, 50.0);

        // 75% duty
        check_duty(8'd75, 8'd100, 75.0);

        // 100% duty
        duty=8'd100; period=8'd100; #500;
        $display("✓ 100%% Duty — pwm_out=%0d PASS", pwm_out);

        $display("================================");
        $display("Day 12 Complete! PWM working!");
        $display("0%% 25%% 50%% 75%% 100%% verified!");
        $display("================================");
        $finish;
    end

endmodule

day12/pwm.vcd
$date
	Tue Jul 28 08:27:56 2026
$end
$version
	Icarus Verilog
$end
$timescale
	1s
$end
$scope module pwm_tb $end
$var wire 1 ! pwm_out $end
$var wire 1 " active $end
$var reg 1 # clk $end
$var reg 8 $ duty [7:0] $end
$var reg 8 % period [7:0] $end
$var reg 1 & rst $end
$var real 1 ' actual_duty $end
$var integer 32 ( high_cnt [31:0] $end
$var integer 32 ) low_cnt [31:0] $end
$var integer 32 * total [31:0] $end
$scope module DUT $end
$var wire 1 # clk $end
$var wire 8 + duty [7:0] $end
$var wire 8 , period [7:0] $end
$var wire 1 & rst $end
$var reg 1 " active $end
$var reg 8 - counter [7:0] $end
$var reg 1 ! pwm_out $end
$upscope $end
$scope task check_duty $end
$var reg 8 . d [7:0] $end
$var reg 8 / p [7:0] $end
$var real 1 0 expected $end
$upscope $end
$upscope $end
$enddefinitions $end
$comment Show the parameter values. $end
$dumpall
$end
#0
$dumpvars
r0 0
bx /
bx .
b0 -
b1100100 ,
b0 +
bx *
bx )
bx (
r0 '
1&
b1100100 %
b0 $
0#
0"
0!
$end
#5
1#
#10
0#
#15
1#
#20
0#
#25
1#
#30
0#
0&
#35
b1 -
1#
#40
0#
#45
b10 -
1#
#50
0#
#55
b11 -
1#
#60
0#
#65
b100 -
1#
#70
0#
#75
b101 -
1#
#80
0#
#85
b110 -
1#
#90
0#
#95
b111 -
1#
#100
0#
#105
b1000 -
1#
#110
0#
#115
b1001 -
1#
#120
0#
#125
b1010 -
1#
#130
0#
#135
b1011 -
1#
#140
0#
#145
b1100 -
1#
#150
0#
#155
b1101 -
1#
#160
0#
#165
b1110 -
1#
#170
0#
#175
b1111 -
1#
#180
0#
#185
b10000 -
1#
#190
0#
#195
b10001 -
1#
#200
0#
#205
b10010 -
1#
#210
0#
#215
b10011 -
1#
#220
0#
#225
b10100 -
1#
#230
0#
#235
b10101 -
1#
#240
0#
#245
b10110 -
1#
#250
0#
#255
b10111 -
1#
#260
0#
#265
b11000 -
1#
#270
0#
#275
b11001 -
1#
#280
0#
#285
b11010 -
1#
#290
0#
#295
b11011 -
1#
#300
0#
#305
b11100 -
1#
#310
0#
#315
b11101 -
1#
#320
0#
#325
b11110 -
1#
#330
0#
#335
b11111 -
1#
#340
0#
#345
b100000 -
1#
#350
0#
#355
b100001 -
1#
#360
0#
#365
b100010 -
1#
#370
0#
#375
b100011 -
1#
#380
0#
#385
b100100 -
1#
#390
0#
#395
b100101 -
1#
#400
0#
#405
b100110 -
1#
#410
0#
#415
b100111 -
1#
#420
0#
#425
b101000 -
1#
#430
0#
#435
b101001 -
1#
#440
0#
#445
b101010 -
1#
#450
0#
#455
b101011 -
1#
#460
0#
#465
b101100 -
1#
#470
0#
#475
b101101 -
1#
#480
0#
#485
b101110 -
1#
#490
0#
#495
b101111 -
1#
#500
0#
#505
b110000 -
1#
#510
0#
#515
b110001 -
1#
#520
0#
#525
b110010 -
1#
#530
0#
#535
b110011 -
1#
#540
0#
#545
b110100 -
1#
#550
0#
b0 )
b0 (
b11001 $
b11001 +
r25 0
b1100100 /
b11001 .
#555
1"
b110101 -
1#
#560
0#
#565
b110110 -
1#
#570
0#
#575
b110111 -
b1 )
1#
#580
0#
#585
b111000 -
b10 )
1#
#590
0#
#595
b111001 -
b11 )
1#
#600
0#
#605
b111010 -
b100 )
1#
#610
0#
#615
b111011 -
b101 )
1#
#620
0#
#625
b111100 -
b110 )
1#
#630
0#
#635
b111101 -
b111 )
1#
#640
0#
#645
b111110 -
b1000 )
1#
#650
0#
#655
b111111 -
b1001 )
1#
#660
0#
#665
b1000000 -
b1010 )
1#
#670
0#
#675
b1000001 -
b1011 )
1#
#680
0#
#685
b1000010 -
b1100 )
1#
#690
0#
#695
b1000011 -
b1101 )
1#
#700
0#
#705
b1000100 -
b1110 )
1#
#710
0#
#715
b1000101 -
b1111 )
1#
#720
0#
#725
b1000110 -
b10000 )
1#
#730
0#
#735
b1000111 -
b10001 )
1#
#740
0#
#745
b1001000 -
b10010 )
1#
#750
0#
#755
b1001001 -
b10011 )
1#
#760
0#
#765
b1001010 -
b10100 )
1#
#770
0#
#775
b1001011 -
b10101 )
1#
#780
0#
#785
b1001100 -
b10110 )
1#
#790
0#
#795
b1001101 -
b10111 )
1#
#800
0#
#805
b1001110 -
b11000 )
1#
#810
0#
#815
b1001111 -
b11001 )
1#
#820
0#
#825
b1010000 -
b11010 )
1#
#830
0#
#835
b1010001 -
b11011 )
1#
#840
0#
#845
b1010010 -
b11100 )
1#
#850
0#
#855
b1010011 -
b11101 )
1#
#860
0#
#865
b1010100 -
b11110 )
1#
#870
0#
#875
b1010101 -
b11111 )
1#
#880
0#
#885
b1010110 -
b100000 )
1#
#890
0#
#895
b1010111 -
b100001 )
1#
#900
0#
#905
b1011000 -
b100010 )
1#
#910
0#
#915
b1011001 -
b100011 )
1#
#920
0#
#925
b1011010 -
b100100 )
1#
#930
0#
#935
b1011011 -
b100101 )
1#
#940
0#
#945
b1011100 -
b100110 )
1#
#950
0#
#955
b1011101 -
b100111 )
1#
#960
0#
#965
b1011110 -
b101000 )
1#
#970
0#
#975
b1011111 -
b101001 )
1#
#980
0#
#985
b1100000 -
b101010 )
1#
#990
0#
#995
b1100001 -
b101011 )
1#
#1000
0#
#1005
b1100010 -
b101100 )
1#
#1010
0#
#1015
b1100011 -
b101101 )
1#
#1020
0#
#1025
b1100100 -
b101110 )
1#
#1030
0#
#1035
b0 -
b101111 )
1#
#1040
0#
#1045
1!
b1 -
b110000 )
1#
#1050
0#
#1055
b10 -
b1 (
1#
#1060
0#
#1065
b11 -
b10 (
1#
#1070
0#
#1075
b100 -
b11 (
1#
#1080
0#
#1085
b101 -
b100 (
1#
#1090
0#
#1095
b110 -
b101 (
1#
#1100
0#
#1105
b111 -
b110 (
1#
#1110
0#
#1115
b1000 -
b111 (
1#
#1120
0#
#1125
b1001 -
b1000 (
1#
#1130
0#
#1135
b1010 -
b1001 (
1#
#1140
0#
#1145
b1011 -
b1010 (
1#
#1150
0#
#1155
b1100 -
b1011 (
1#
#1160
0#
#1165
b1101 -
b1100 (
1#
#1170
0#
#1175
b1110 -
b1101 (
1#
#1180
0#
#1185
b1111 -
b1110 (
1#
#1190
0#
#1195
b10000 -
b1111 (
1#
#1200
0#
#1205
b10001 -
b10000 (
1#
#1210
0#
#1215
b10010 -
b10001 (
1#
#1220
0#
#1225
b10011 -
b10010 (
1#
#1230
0#
#1235
b10100 -
b10011 (
1#
#1240
0#
#1245
b10101 -
b10100 (
1#
#1250
0#
#1255
b10110 -
b10101 (
1#
#1260
0#
#1265
b10111 -
b10110 (
1#
#1270
0#
#1275
b11000 -
b10111 (
1#
#1280
0#
#1285
b11001 -
b11000 (
1#
#1290
0#
#1295
0!
b11010 -
b11001 (
1#
#1300
0#
#1305
b11011 -
b110001 )
1#
#1310
0#
#1315
b11100 -
b110010 )
1#
#1320
0#
#1325
b11101 -
b110011 )
1#
#1330
0#
#1335
b11110 -
b110100 )
1#
#1340
0#
#1345
b11111 -
b110101 )
1#
#1350
0#
#1355
b100000 -
b110110 )
1#
#1360
0#
#1365
b100001 -
b110111 )
1#
#1370
0#
#1375
b100010 -
b111000 )
1#
#1380
0#
#1385
b100011 -
b111001 )
1#
#1390
0#
#1395
b100100 -
b111010 )
1#
#1400
0#
#1405
b100101 -
b111011 )
1#
#1410
0#
#1415
b100110 -
b111100 )
1#
#1420
0#
#1425
b100111 -
b111101 )
1#
#1430
0#
#1435
b101000 -
b111110 )
1#
#1440
0#
#1445
b101001 -
b111111 )
1#
#1450
0#
#1455
b101010 -
b1000000 )
1#
#1460
0#
#1465
b101011 -
b1000001 )
1#
#1470
0#
#1475
b101100 -
b1000010 )
1#
#1480
0#
#1485
b101101 -
b1000011 )
1#
#1490
0#
#1495
b101110 -
b1000100 )
1#
#1500
0#
#1505
b101111 -
b1000101 )
1#
#1510
0#
#1515
b110000 -
b1000110 )
1#
#1520
0#
#1525
b110001 -
b1000111 )
1#
#1530
0#
#1535
b110010 -
b1001000 )
1#
#1540
0#
#1545
b110011 -
b1001001 )
1#
#1550
0#
#1555
b110100 -
b1001010 )
1#
#1560
0#
#1565
b110101 -
b1001011 )
1#
#1570
0#
#1575
b110110 -
b1001100 )
1#
#1580
0#
#1585
b110111 -
b1001101 )
1#
#1590
0#
#1595
b111000 -
b1001110 )
1#
#1600
0#
#1605
b111001 -
b1001111 )
1#
#1610
0#
#1615
b111010 -
b1010000 )
1#
#1620
0#
#1625
b111011 -
b1010001 )
1#
#1630
0#
#1635
b111100 -
b1010010 )
1#
#1640
0#
#1645
b111101 -
b1010011 )
1#
#1650
0#
#1655
b111110 -
b1010100 )
1#
#1660
0#
#1665
b111111 -
b1010101 )
1#
#1670
0#
#1675
b1000000 -
b1010110 )
1#
#1680
0#
#1685
b1000001 -
b1010111 )
1#
#1690
0#
#1695
b1000010 -
b1011000 )
1#
#1700
0#
#1705
b1000011 -
b1011001 )
1#
#1710
0#
#1715
b1000100 -
b1011010 )
1#
#1720
0#
#1725
b1000101 -
b1011011 )
1#
#1730
0#
#1735
b1000110 -
b1011100 )
1#
#1740
0#
#1745
b1000111 -
b1011101 )
1#
#1750
0#
#1755
b1001000 -
b1011110 )
1#
#1760
0#
#1765
b1001001 -
b1011111 )
1#
#1770
0#
#1775
b1001010 -
b1100000 )
1#
#1780
0#
#1785
b1001011 -
b1100001 )
1#
#1790
0#
#1795
b1001100 -
b1100010 )
1#
#1800
0#
#1805
b1001101 -
b1100011 )
1#
#1810
0#
#1815
b1001110 -
b1100100 )
1#
#1820
0#
#1825
b1001111 -
b1100101 )
1#
#1830
0#
#1835
b1010000 -
b1100110 )
1#
#1840
0#
#1845
b1010001 -
b1100111 )
1#
#1850
0#
#1855
b1010010 -
b1101000 )
1#
#1860
0#
#1865
b1010011 -
b1101001 )
1#
#1870
0#
#1875
b1010100 -
b1101010 )
1#
#1880
0#
#1885
b1010101 -
b1101011 )
1#
#1890
0#
#1895
b1010110 -
b1101100 )
1#
#1900
0#
#1905
b1010111 -
b1101101 )
1#
#1910
0#
#1915
b1011000 -
b1101110 )
1#
#1920
0#
#1925
b1011001 -
b1101111 )
1#
#1930
0#
#1935
b1011010 -
b1110000 )
1#
#1940
0#
#1945
b1011011 -
b1110001 )
1#
#1950
0#
#1955
b1011100 -
b1110010 )
1#
#1960
0#
#1965
b1011101 -
b1110011 )
1#
#1970
0#
#1975
b1011110 -
b1110100 )
1#
#1980
0#
#1985
b1011111 -
b1110101 )
1#
#1990
0#
#1995
b1100000 -
b1110110 )
1#
#2000
0#
#2005
b1100001 -
b1110111 )
1#
#2010
0#
#2015
b1100010 -
b1111000 )
1#
#2020
0#
#2025
b1100011 -
b1111001 )
1#
#2030
0#
#2035
b1100100 -
b1111010 )
1#
#2040
0#
#2045
b0 -
b1111011 )
1#
#2050
0#
#2055
1!
b1 -
b1111100 )
1#
#2060
0#
#2065
b10 -
b11010 (
1#
#2070
0#
#2075
b11 -
b11011 (
1#
#2080
0#
#2085
b100 -
b11100 (
1#
#2090
0#
#2095
b101 -
b11101 (
1#
#2100
0#
#2105
b110 -
b11110 (
1#
#2110
0#
#2115
b111 -
b11111 (
1#
#2120
0#
#2125
b1000 -
b100000 (
1#
#2130
0#
#2135
b1001 -
b100001 (
1#
#2140
0#
#2145
b1010 -
b100010 (
1#
#2150
0#
#2155
b1011 -
b100011 (
1#
#2160
0#
#2165
b1100 -
b100100 (
1#
#2170
0#
#2175
b1101 -
b100101 (
1#
#2180
0#
#2185
b1110 -
b100110 (
1#
#2190
0#
#2195
b1111 -
b100111 (
1#
#2200
0#
#2205
b10000 -
b101000 (
1#
#2210
0#
#2215
b10001 -
b101001 (
1#
#2220
0#
#2225
b10010 -
b101010 (
1#
#2230
0#
#2235
b10011 -
b101011 (
1#
#2240
0#
#2245
b10100 -
b101100 (
1#
#2250
0#
#2255
b10101 -
b101101 (
1#
#2260
0#
#2265
b10110 -
b101110 (
1#
#2270
0#
#2275
b10111 -
b101111 (
1#
#2280
0#
#2285
b11000 -
b110000 (
1#
#2290
0#
#2295
b11001 -
b110001 (
1#
#2300
0#
#2305
0!
b11010 -
b110010 (
1#
#2310
0#
#2315
b11011 -
b1111101 )
1#
#2320
0#
#2325
b11100 -
b1111110 )
1#
#2330
0#
#2335
b11101 -
b1111111 )
1#
#2340
0#
#2345
b11110 -
b10000000 )
1#
#2350
0#
#2355
b11111 -
b10000001 )
1#
#2360
0#
#2365
b100000 -
b10000010 )
1#
#2370
0#
#2375
b100001 -
b10000011 )
1#
#2380
0#
#2385
b100010 -
b10000100 )
1#
#2390
0#
#2395
b100011 -
b10000101 )
1#
#2400
0#
#2405
b100100 -
b10000110 )
1#
#2410
0#
#2415
b100101 -
b10000111 )
1#
#2420
0#
#2425
b100110 -
b10001000 )
1#
#2430
0#
#2435
b100111 -
b10001001 )
1#
#2440
0#
#2445
b101000 -
b10001010 )
1#
#2450
0#
#2455
b101001 -
b10001011 )
1#
#2460
0#
#2465
b101010 -
b10001100 )
1#
#2470
0#
#2475
b101011 -
b10001101 )
1#
#2480
0#
#2485
b101100 -
b10001110 )
1#
#2490
0#
#2495
b101101 -
b10001111 )
1#
#2500
0#
#2505
b101110 -
b10010000 )
1#
#2510
0#
#2515
b101111 -
b10010001 )
1#
#2520
0#
#2525
b110000 -
b10010010 )
1#
#2530
0#
#2535
b110001 -
b10010011 )
1#
#2540
0#
#2545
b110010 -
b10010100 )
1#
#2550
0#
#2555
b110011 -
b10010101 )
1#
#2560
0#
#2565
b110100 -
b10010110 )
1#
#2570
0#
#2575
b110101 -
b10010111 )
1#
#2580
0#
#2585
b110110 -
b10011000 )
1#
#2590
0#
#2595
b110111 -
b10011001 )
1#
#2600
0#
#2605
b111000 -
b10011010 )
1#
#2610
0#
#2615
b111001 -
b10011011 )
1#
#2620
0#
#2625
b111010 -
b10011100 )
1#
#2630
0#
#2635
b111011 -
b10011101 )
1#
#2640
0#
#2645
b111100 -
b10011110 )
1#
#2650
0#
#2655
b111101 -
b10011111 )
1#
#2660
0#
#2665
b111110 -
b10100000 )
1#
#2670
0#
#2675
b111111 -
b10100001 )
1#
#2680
0#
#2685
b1000000 -
b10100010 )
1#
#2690
0#
#2695
b1000001 -
b10100011 )
1#
#2700
0#
#2705
b1000010 -
b10100100 )
1#
#2710
0#
#2715
b1000011 -
b10100101 )
1#
#2720
0#
#2725
b1000100 -
b10100110 )
1#
#2730
0#
#2735
b1000101 -
b10100111 )
1#
#2740
0#
#2745
b1000110 -
b10101000 )
1#
#2750
0#
#2755
b1000111 -
b10101001 )
1#
#2760
0#
#2765
b1001000 -
b10101010 )
1#
#2770
0#
#2775
b1001001 -
b10101011 )
1#
#2780
0#
#2785
b1001010 -
b10101100 )
1#
#2790
0#
#2795
b1001011 -
b10101101 )
1#
#2800
0#
#2805
b1001100 -
b10101110 )
1#
#2810
0#
#2815
b1001101 -
b10101111 )
1#
#2820
0#
#2825
b1001110 -
b10110000 )
1#
#2830
0#
#2835
b1001111 -
b10110001 )
1#
#2840
0#
#2845
b1010000 -
b10110010 )
1#
#2850
0#
#2855
b1010001 -
b10110011 )
1#
#2860
0#
#2865
b1010010 -
b10110100 )
1#
#2870
0#
#2875
b1010011 -
b10110101 )
1#
#2880
0#
#2885
b1010100 -
b10110110 )
1#
#2890
0#
#2895
b1010101 -
b10110111 )
1#
#2900
0#
#2905
b1010110 -
b10111000 )
1#
#2910
0#
#2915
b1010111 -
b10111001 )
1#
#2920
0#
#2925
b1011000 -
b10111010 )
1#
#2930
0#
#2935
b1011001 -
b10111011 )
1#
#2940
0#
#2945
b1011010 -
b10111100 )
1#
#2950
0#
#2955
b1011011 -
b10111101 )
1#
#2960
0#
#2965
b1011100 -
b10111110 )
1#
#2970
0#
#2975
b1011101 -
b10111111 )
1#
#2980
0#
#2985
b1011110 -
b11000000 )
1#
#2990
0#
#2995
b1011111 -
b11000001 )
1#
#3000
0#
#3005
b1100000 -
b11000010 )
1#
#3010
0#
#3015
b1100001 -
b11000011 )
1#
#3020
0#
#3025
b1100010 -
b11000100 )
1#
#3030
0#
#3035
b1100011 -
b11000101 )
1#
#3040
0#
#3045
b1100100 -
b11000110 )
1#
#3050
0#
#3055
b0 -
b11000111 )
1#
#3060
0#
#3065
1!
b1 -
b11001000 )
1#
#3070
0#
#3075
b10 -
b110011 (
1#
#3080
0#
#3085
b11 -
b110100 (
1#
#3090
0#
#3095
b100 -
b110101 (
1#
#3100
0#
#3105
b101 -
b110110 (
1#
#3110
0#
#3115
b110 -
b110111 (
1#
#3120
0#
#3125
b111 -
b0 )
b110010 $
b110010 +
r50 0
b110010 .
r21.875 '
b100000000 *
b0 (
1#
#3130
0#
#3135
b1000 -
1#
#3140
0#
#3145
b1001 -
b1 (
1#
#3150
0#
#3155
b1010 -
b10 (
1#
#3160
0#
#3165
b1011 -
b11 (
1#
#3170
0#
#3175
b1100 -
b100 (
1#
#3180
0#
#3185
b1101 -
b101 (
1#
#3190
0#
#3195
b1110 -
b110 (
1#
#3200
0#
#3205
b1111 -
b111 (
1#
#3210
0#
#3215
b10000 -
b1000 (
1#
#3220
0#
#3225
b10001 -
b1001 (
1#
#3230
0#
#3235
b10010 -
b1010 (
1#
#3240
0#
#3245
b10011 -
b1011 (
1#
#3250
0#
#3255
b10100 -
b1100 (
1#
#3260
0#
#3265
b10101 -
b1101 (
1#
#3270
0#
#3275
b10110 -
b1110 (
1#
#3280
0#
#3285
b10111 -
b1111 (
1#
#3290
0#
#3295
b11000 -
b10000 (
1#
#3300
0#
#3305
b11001 -
b10001 (
1#
#3310
0#
#3315
b11010 -
b10010 (
1#
#3320
0#
#3325
b11011 -
b10011 (
1#
#3330
0#
#3335
b11100 -
b10100 (
1#
#3340
0#
#3345
b11101 -
b10101 (
1#
#3350
0#
#3355
b11110 -
b10110 (
1#
#3360
0#
#3365
b11111 -
b10111 (
1#
#3370
0#
#3375
b100000 -
b11000 (
1#
#3380
0#
#3385
b100001 -
b11001 (
1#
#3390
0#
#3395
b100010 -
b11010 (
1#
#3400
0#
#3405
b100011 -
b11011 (
1#
#3410
0#
#3415
b100100 -
b11100 (
1#
#3420
0#
#3425
b100101 -
b11101 (
1#
#3430
0#
#3435
b100110 -
b11110 (
1#
#3440
0#
#3445
b100111 -
b11111 (
1#
#3450
0#
#3455
b101000 -
b100000 (
1#
#3460
0#
#3465
b101001 -
b100001 (
1#
#3470
0#
#3475
b101010 -
b100010 (
1#
#3480
0#
#3485
b101011 -
b100011 (
1#
#3490
0#
#3495
b101100 -
b100100 (
1#
#3500
0#
#3505
b101101 -
b100101 (
1#
#3510
0#
#3515
b101110 -
b100110 (
1#
#3520
0#
#3525
b101111 -
b100111 (
1#
#3530
0#
#3535
b110000 -
b101000 (
1#
#3540
0#
#3545
b110001 -
b101001 (
1#
#3550
0#
#3555
b110010 -
b101010 (
1#
#3560
0#
#3565
0!
b110011 -
b101011 (
1#
#3570
0#
#3575
b110100 -
b1 )
1#
#3580
0#
#3585
b110101 -
b10 )
1#
#3590
0#
#3595
b110110 -
b11 )
1#
#3600
0#
#3605
b110111 -
b100 )
1#
#3610
0#
#3615
b111000 -
b101 )
1#
#3620
0#
#3625
b111001 -
b110 )
1#
#3630
0#
#3635
b111010 -
b111 )
1#
#3640
0#
#3645
b111011 -
b1000 )
1#
#3650
0#
#3655
b111100 -
b1001 )
1#
#3660
0#
#3665
b111101 -
b1010 )
1#
#3670
0#
#3675
b111110 -
b1011 )
1#
#3680
0#
#3685
b111111 -
b1100 )
1#
#3690
0#
#3695
b1000000 -
b1101 )
1#
#3700
0#
#3705
b1000001 -
b1110 )
1#
#3710
0#
#3715
b1000010 -
b1111 )
1#
#3720
0#
#3725
b1000011 -
b10000 )
1#
#3730
0#
#3735
b1000100 -
b10001 )
1#
#3740
0#
#3745
b1000101 -
b10010 )
1#
#3750
0#
#3755
b1000110 -
b10011 )
1#
#3760
0#
#3765
b1000111 -
b10100 )
1#
#3770
0#
#3775
b1001000 -
b10101 )
1#
#3780
0#
#3785
b1001001 -
b10110 )
1#
#3790
0#
#3795
b1001010 -
b10111 )
1#
#3800
0#
#3805
b1001011 -
b11000 )
1#
#3810
0#
#3815
b1001100 -
b11001 )
1#
#3820
0#
#3825
b1001101 -
b11010 )
1#
#3830
0#
#3835
b1001110 -
b11011 )
1#
#3840
0#
#3845
b1001111 -
b11100 )
1#
#3850
0#
#3855
b1010000 -
b11101 )
1#
#3860
0#
#3865
b1010001 -
b11110 )
1#
#3870
0#
#3875
b1010010 -
b11111 )
1#
#3880
0#
#3885
b1010011 -
b100000 )
1#
#3890
0#
#3895
b1010100 -
b100001 )
1#
#3900
0#
#3905
b1010101 -
b100010 )
1#
#3910
0#
#3915
b1010110 -
b100011 )
1#
#3920
0#
#3925
b1010111 -
b100100 )
1#
#3930
0#
#3935
b1011000 -
b100101 )
1#
#3940
0#
#3945
b1011001 -
b100110 )
1#
#3950
0#
#3955
b1011010 -
b100111 )
1#
#3960
0#
#3965
b1011011 -
b101000 )
1#
#3970
0#
#3975
b1011100 -
b101001 )
1#
#3980
0#
#3985
b1011101 -
b101010 )
1#
#3990
0#
#3995
b1011110 -
b101011 )
1#
#4000
0#
#4005
b1011111 -
b101100 )
1#
#4010
0#
#4015
b1100000 -
b101101 )
1#
#4020
0#
#4025
b1100001 -
b101110 )
1#
#4030
0#
#4035
b1100010 -
b101111 )
1#
#4040
0#
#4045
b1100011 -
b110000 )
1#
#4050
0#
#4055
b1100100 -
b110001 )
1#
#4060
0#
#4065
b0 -
b110010 )
1#
#4070
0#
#4075
1!
b1 -
b110011 )
1#
#4080
0#
#4085
b10 -
b101100 (
1#
#4090
0#
#4095
b11 -
b101101 (
1#
#4100
0#
#4105
b100 -
b101110 (
1#
#4110
0#
#4115
b101 -
b101111 (
1#
#4120
0#
#4125
b110 -
b110000 (
1#
#4130
0#
#4135
b111 -
b110001 (
1#
#4140
0#
#4145
b1000 -
b110010 (
1#
#4150
0#
#4155
b1001 -
b110011 (
1#
#4160
0#
#4165
b1010 -
b110100 (
1#
#4170
0#
#4175
b1011 -
b110101 (
1#
#4180
0#
#4185
b1100 -
b110110 (
1#
#4190
0#
#4195
b1101 -
b110111 (
1#
#4200
0#
#4205
b1110 -
b111000 (
1#
#4210
0#
#4215
b1111 -
b111001 (
1#
#4220
0#
#4225
b10000 -
b111010 (
1#
#4230
0#
#4235
b10001 -
b111011 (
1#
#4240
0#
#4245
b10010 -
b111100 (
1#
#4250
0#
#4255
b10011 -
b111101 (
1#
#4260
0#
#4265
b10100 -
b111110 (
1#
#4270
0#
#4275
b10101 -
b111111 (
1#
#4280
0#
#4285
b10110 -
b1000000 (
1#
#4290
0#
#4295
b10111 -
b1000001 (
1#
#4300
0#
#4305
b11000 -
b1000010 (
1#
#4310
0#
#4315
b11001 -
b1000011 (
1#
#4320
0#
#4325
b11010 -
b1000100 (
1#
#4330
0#
#4335
b11011 -
b1000101 (
1#
#4340
0#
#4345
b11100 -
b1000110 (
1#
#4350
0#
#4355
b11101 -
b1000111 (
1#
#4360
0#
#4365
b11110 -
b1001000 (
1#
#4370
0#
#4375
b11111 -
b1001001 (
1#
#4380
0#
#4385
b100000 -
b1001010 (
1#
#4390
0#
#4395
b100001 -
b1001011 (
1#
#4400
0#
#4405
b100010 -
b1001100 (
1#
#4410
0#
#4415
b100011 -
b1001101 (
1#
#4420
0#
#4425
b100100 -
b1001110 (
1#
#4430
0#
#4435
b100101 -
b1001111 (
1#
#4440
0#
#4445
b100110 -
b1010000 (
1#
#4450
0#
#4455
b100111 -
b1010001 (
1#
#4460
0#
#4465
b101000 -
b1010010 (
1#
#4470
0#
#4475
b101001 -
b1010011 (
1#
#4480
0#
#4485
b101010 -
b1010100 (
1#
#4490
0#
#4495
b101011 -
b1010101 (
1#
#4500
0#
#4505
b101100 -
b1010110 (
1#
#4510
0#
#4515
b101101 -
b1010111 (
1#
#4520
0#
#4525
b101110 -
b1011000 (
1#
#4530
0#
#4535
b101111 -
b1011001 (
1#
#4540
0#
#4545
b110000 -
b1011010 (
1#
#4550
0#
#4555
b110001 -
b1011011 (
1#
#4560
0#
#4565
b110010 -
b1011100 (
1#
#4570
0#
#4575
0!
b110011 -
b1011101 (
1#
#4580
0#
#4585
b110100 -
b110100 )
1#
#4590
0#
#4595
b110101 -
b110101 )
1#
#4600
0#
#4605
b110110 -
b110110 )
1#
#4610
0#
#4615
b110111 -
b110111 )
1#
#4620
0#
#4625
b111000 -
b111000 )
1#
#4630
0#
#4635
b111001 -
b111001 )
1#
#4640
0#
#4645
b111010 -
b111010 )
1#
#4650
0#
#4655
b111011 -
b111011 )
1#
#4660
0#
#4665
b111100 -
b111100 )
1#
#4670
0#
#4675
b111101 -
b111101 )
1#
#4680
0#
#4685
b111110 -
b111110 )
1#
#4690
0#
#4695
b111111 -
b111111 )
1#
#4700
0#
#4705
b1000000 -
b1000000 )
1#
#4710
0#
#4715
b1000001 -
b1000001 )
1#
#4720
0#
#4725
b1000010 -
b1000010 )
1#
#4730
0#
#4735
b1000011 -
b1000011 )
1#
#4740
0#
#4745
b1000100 -
b1000100 )
1#
#4750
0#
#4755
b1000101 -
b1000101 )
1#
#4760
0#
#4765
b1000110 -
b1000110 )
1#
#4770
0#
#4775
b1000111 -
b1000111 )
1#
#4780
0#
#4785
b1001000 -
b1001000 )
1#
#4790
0#
#4795
b1001001 -
b1001001 )
1#
#4800
0#
#4805
b1001010 -
b1001010 )
1#
#4810
0#
#4815
b1001011 -
b1001011 )
1#
#4820
0#
#4825
b1001100 -
b1001100 )
1#
#4830
0#
#4835
b1001101 -
b1001101 )
1#
#4840
0#
#4845
b1001110 -
b1001110 )
1#
#4850
0#
#4855
b1001111 -
b1001111 )
1#
#4860
0#
#4865
b1010000 -
b1010000 )
1#
#4870
0#
#4875
b1010001 -
b1010001 )
1#
#4880
0#
#4885
b1010010 -
b1010010 )
1#
#4890
0#
#4895
b1010011 -
b1010011 )
1#
#4900
0#
#4905
b1010100 -
b1010100 )
1#
#4910
0#
#4915
b1010101 -
b1010101 )
1#
#4920
0#
#4925
b1010110 -
b1010110 )
1#
#4930
0#
#4935
b1010111 -
b1010111 )
1#
#4940
0#
#4945
b1011000 -
b1011000 )
1#
#4950
0#
#4955
b1011001 -
b1011001 )
1#
#4960
0#
#4965
b1011010 -
b1011010 )
1#
#4970
0#
#4975
b1011011 -
b1011011 )
1#
#4980
0#
#4985
b1011100 -
b1011100 )
1#
#4990
0#
#4995
b1011101 -
b1011101 )
1#
#5000
0#
#5005
b1011110 -
b1011110 )
1#
#5010
0#
#5015
b1011111 -
b1011111 )
1#
#5020
0#
#5025
b1100000 -
b1100000 )
1#
#5030
0#
#5035
b1100001 -
b1100001 )
1#
#5040
0#
#5045
b1100010 -
b1100010 )
1#
#5050
0#
#5055
b1100011 -
b1100011 )
1#
#5060
0#
#5065
b1100100 -
b1100100 )
1#
#5070
0#
#5075
b0 -
b1100101 )
1#
#5080
0#
#5085
1!
b1 -
b1100110 )
1#
#5090
0#
#5095
b10 -
b1011110 (
1#
#5100
0#
#5105
b11 -
b1011111 (
1#
#5110
0#
#5115
b100 -
b1100000 (
1#
#5120
0#
#5125
b101 -
b1100001 (
1#
#5130
0#
#5135
b110 -
b1100010 (
1#
#5140
0#
